[
  {
    "I_D":1609,
    "FLAG_TSUNAMI":"",
    "YEAR":1812,
    "MONTH":12,
    "DAY":8,
    "HOUR":15,
    "MINUTE":null,
    "SECOND":null,
    "FOCAL_DEPTH":null,
    "EQ_PRIMARY":6.9,
    "EQ_MAG_MW":null,
    "EQ_MAG_MS":null,
    "EQ_MAG_MB":null,
    "EQ_MAG_ML":6.9,
    "EQ_MAG_MFA":"",
    "EQ_MAG_UNK":null,
    "INTENSITY":8,
    "COUNTRY":"USA",
    "STATE":"CA",
    "LOCATION_NAME":"CALIFORNIA:   SAN JUAN CAPISTRANO",
    "LATITUDE":"34.37",
    "LONGITUDE":"-117.65",
    "REGION_CODE":"150",
    "DEATHS":40,
    "DEATHS_DESCRIPTION":1,
    "MISSING":null,
    "MISSING_DESCRIPTION":"",
    "INJURIES":null,
    "INJURIES_DESCRIPTION":null,
    "DAMAGE_MILLIONS_DOLLARS":null,
    "DAMAGE_DESCRIPTION":2,
    "HOUSES_DESTROYED":null,
    "HOUSES_DESTROYED_DESCRIPTION":null,
    "HOUSES_DAMAGED":null,
    "HOUSES_DAMAGED_DESCRIPTION":1,
    "TOTAL_DEATHS":40,
    "TOTAL_DEATHS_DESCRIPTION":1,
    "TOTAL_MISSING":null,
    "TOTAL_MISSING_DESCRIPTION":"",
    "TOTAL_INJURIES":null,
    "TOTAL_INJURIES_DESCRIPTION":null,
    "TOTAL_DAMAGE_MILLIONS_DOLLARS":null,
    "TOTAL_DAMAGE_DESCRIPTION":2,
    "TOTAL_HOUSES_DESTROYED":null,
    "TOTAL_HOUSES_DESTROYED_DESCRIPTION":null,
    "TOTAL_HOUSES_DAMAGED":null,
    "TOTAL_HOUSES_DAMAGED_DESCRIPTION":1
  },
  {
    "I_D":1610,
    "FLAG_TSUNAMI":"Tsu",
    "YEAR":1812,
    "MONTH":12,
    "DAY":21,
    "HOUR":19,
    "MINUTE":null,
    "SECOND":null,
    "FOCAL_DEPTH":null,
    "EQ_PRIMARY":7.5,
    "EQ_MAG_MW":null,
    "EQ_MAG_MS":7.5,
    "EQ_MAG_MB":null,
    "EQ_MAG_ML":7.1,
    "EQ_MAG_MFA":"",
    "EQ_MAG_UNK":7.7,
    "INTENSITY":8,
    "COUNTRY":"USA",
    "STATE":"CA",
    "LOCATION_NAME":"CALIFORNIA:   PURISIMA",
    "LATITUDE":"34.2",
    "LONGITUDE":"-119.9",
    "REGION_CODE":"150",
    "DEATHS":1,
    "DEATHS_DESCRIPTION":1,
    "MISSING":null,
    "MISSING_DESCRIPTION":"",
    "INJURIES":null,
    "INJURIES_DESCRIPTION":1,
    "DAMAGE_MILLIONS_DOLLARS":null,
    "DAMAGE_DESCRIPTION":2,
    "HOUSES_DESTROYED":null,
    "HOUSES_DESTROYED_DESCRIPTION":null,
    "HOUSES_DAMAGED":100,
    "HOUSES_DAMAGED_DESCRIPTION":1,
    "TOTAL_DEATHS":1,
    "TOTAL_DEATHS_DESCRIPTION":1,
    "TOTAL_MISSING":null,
    "TOTAL_MISSING_DESCRIPTION":"",
    "TOTAL_INJURIES":null,
    "TOTAL_INJURIES_DESCRIPTION":1,
    "TOTAL_DAMAGE_MILLIONS_DOLLARS":null,
    "TOTAL_DAMAGE_DESCRIPTION":2,
    "TOTAL_HOUSES_DESTROYED":null,
    "TOTAL_HOUSES_DESTROYED_DESCRIPTION":1,
    "TOTAL_HOUSES_DAMAGED":100,
    "TOTAL_HOUSES_DAMAGED_DESCRIPTION":1
  },
  {
    "I_D":1808,
    "FLAG_TSUNAMI":"",
    "YEAR":1838,
    "MONTH":6,
    "DAY":null,
    "HOUR":null,
    "MINUTE":null,
    "SECOND":null,
    "FOCAL_DEPTH":null,
    "EQ_PRIMARY":7,
    "EQ_MAG_MW":null,
    "EQ_MAG_MS":null,
    "EQ_MAG_MB":null,
    "EQ_MAG_ML":7,
    "EQ_MAG_MFA":"",
    "EQ_MAG_UNK":null,
    "INTENSITY":8,
    "COUNTRY":"USA",
    "STATE":"CA",
    "LOCATION_NAME":"CALIFORNIA:  SAN FRANCISCO",
    "LATITUDE":"SAN JOSE",
    "LONGITUDE":"SANTA CLARA",
    "REGION_CODE":"37.6",
    "DEATHS":-122.4,
    "DEATHS_DESCRIPTION":150,
    "MISSING":null,
    "MISSING_DESCRIPTION":"",
    "INJURIES":null,
    "INJURIES_DESCRIPTION":null,
    "DAMAGE_MILLIONS_DOLLARS":null,
    "DAMAGE_DESCRIPTION":null,
    "HOUSES_DESTROYED":null,
    "HOUSES_DESTROYED_DESCRIPTION":1,
    "HOUSES_DAMAGED":null,
    "HOUSES_DAMAGED_DESCRIPTION":null,
    "TOTAL_DEATHS":null,
    "TOTAL_DEATHS_DESCRIPTION":null,
    "TOTAL_MISSING":null,
    "TOTAL_MISSING_DESCRIPTION":"",
    "TOTAL_INJURIES":null,
    "TOTAL_INJURIES_DESCRIPTION":null,
    "TOTAL_DAMAGE_MILLIONS_DOLLARS":null,
    "TOTAL_DAMAGE_DESCRIPTION":null,
    "TOTAL_HOUSES_DESTROYED":null,
    "TOTAL_HOUSES_DESTROYED_DESCRIPTION":1,
    "TOTAL_HOUSES_DAMAGED":null,
    "TOTAL_HOUSES_DAMAGED_DESCRIPTION":null
  },
  {
    "I_D":1984,
    "FLAG_TSUNAMI":"Tsu",
    "YEAR":1855,
    "MONTH":7,
    "DAY":11,
    "HOUR":4,
    "MINUTE":15,
    "SECOND":null,
    "FOCAL_DEPTH":null,
    "EQ_PRIMARY":6,
    "EQ_MAG_MW":null,
    "EQ_MAG_MS":null,
    "EQ_MAG_MB":null,
    "EQ_MAG_ML":6,
    "EQ_MAG_MFA":"",
    "EQ_MAG_UNK":null,
    "INTENSITY":8,
    "COUNTRY":"USA",
    "STATE":"CA",
    "LOCATION_NAME":"CALIFORNIA:  LOS ANGELES",
    "LATITUDE":"34.1",
    "LONGITUDE":"-118.1",
    "REGION_CODE":"150",
    "DEATHS":null,
    "DEATHS_DESCRIPTION":null,
    "MISSING":null,
    "MISSING_DESCRIPTION":"",
    "INJURIES":null,
    "INJURIES_DESCRIPTION":null,
    "DAMAGE_MILLIONS_DOLLARS":null,
    "DAMAGE_DESCRIPTION":2,
    "HOUSES_DESTROYED":1,
    "HOUSES_DESTROYED_DESCRIPTION":1,
    "HOUSES_DAMAGED":26,
    "HOUSES_DAMAGED_DESCRIPTION":1,
    "TOTAL_DEATHS":null,
    "TOTAL_DEATHS_DESCRIPTION":null,
    "TOTAL_MISSING":null,
    "TOTAL_MISSING_DESCRIPTION":"",
    "TOTAL_INJURIES":null,
    "TOTAL_INJURIES_DESCRIPTION":null,
    "TOTAL_DAMAGE_MILLIONS_DOLLARS":null,
    "TOTAL_DAMAGE_DESCRIPTION":2,
    "TOTAL_HOUSES_DESTROYED":1,
    "TOTAL_HOUSES_DESTROYED_DESCRIPTION":1,
    "TOTAL_HOUSES_DAMAGED":26,
    "TOTAL_HOUSES_DAMAGED_DESCRIPTION":1
  },
  {
    "I_D":6977,
    "FLAG_TSUNAMI":"Tsu",
    "YEAR":1856,
    "MONTH":2,
    "DAY":15,
    "HOUR":13,
    "MINUTE":25,
    "SECOND":null,
    "FOCAL_DEPTH":null,
    "EQ_PRIMARY":5.5,
    "EQ_MAG_MW":null,
    "EQ_MAG_MS":null,
    "EQ_MAG_MB":null,
    "EQ_MAG_ML":5.5,
    "EQ_MAG_MFA":"",
    "EQ_MAG_UNK":null,
    "INTENSITY":7,
    "COUNTRY":"USA",
    "STATE":"CA",
    "LOCATION_NAME":"CALIFORNIA:  NORTHERN",
    "LATITUDE":"37.5",
    "LONGITUDE":"-122.3",
    "REGION_CODE":"150",
    "DEATHS":null,
    "DEATHS_DESCRIPTION":null,
    "MISSING":null,
    "MISSING_DESCRIPTION":"",
    "INJURIES":null,
    "INJURIES_DESCRIPTION":null,
    "DAMAGE_MILLIONS_DOLLARS":null,
    "DAMAGE_DESCRIPTION":null,
    "HOUSES_DESTROYED":null,
    "HOUSES_DESTROYED_DESCRIPTION":null,
    "HOUSES_DAMAGED":null,
    "HOUSES_DAMAGED_DESCRIPTION":null,
    "TOTAL_DEATHS":null,
    "TOTAL_DEATHS_DESCRIPTION":null,
    "TOTAL_MISSING":null,
    "TOTAL_MISSING_DESCRIPTION":"",
    "TOTAL_INJURIES":null,
    "TOTAL_INJURIES_DESCRIPTION":null,
    "TOTAL_DAMAGE_MILLIONS_DOLLARS":null,
    "TOTAL_DAMAGE_DESCRIPTION":1,
    "TOTAL_HOUSES_DESTROYED":null,
    "TOTAL_HOUSES_DESTROYED_DESCRIPTION":null,
    "TOTAL_HOUSES_DAMAGED":null,
    "TOTAL_HOUSES_DAMAGED_DESCRIPTION":null
  },
  {
    "I_D":2007,
    "FLAG_TSUNAMI":"",
    "YEAR":1857,
    "MONTH":1,
    "DAY":9,
    "HOUR":10,
    "MINUTE":13,
    "SECOND":    ,
    "FOCAL_DEPTH":null,
    "EQ_PRIMARY":8.3,
    "EQ_MAG_MW":null,
    "EQ_MAG_MS":null,
    "EQ_MAG_MB":null,
    "EQ_MAG_ML":null,
    "EQ_MAG_MFA":"",
    "EQ_MAG_UNK":8.3,
    "INTENSITY":7,
    "COUNTRY":"USA",
    "STATE":"CA",
    "LOCATION_NAME":"CALIFORNIA:  SAN FRANCISCO",
    "LATITUDE":"35",
    "LONGITUDE":"-119",
    "REGION_CODE":"150",
    "DEATHS":null,
    "DEATHS_DESCRIPTION":null,
    "MISSING":null,
    "MISSING_DESCRIPTION":"",
    "INJURIES":null,
    "INJURIES_DESCRIPTION":null,
    "DAMAGE_MILLIONS_DOLLARS":null,
    "DAMAGE_DESCRIPTION":3,
    "HOUSES_DESTROYED":null,
    "HOUSES_DESTROYED_DESCRIPTION":null,
    "HOUSES_DAMAGED":null,
    "HOUSES_DAMAGED_DESCRIPTION":null,
    "TOTAL_DEATHS":null,
    "TOTAL_DEATHS_DESCRIPTION":null,
    "TOTAL_MISSING":null,
    "TOTAL_MISSING_DESCRIPTION":"",
    "TOTAL_INJURIES":null,
    "TOTAL_INJURIES_DESCRIPTION":null,
    "TOTAL_DAMAGE_MILLIONS_DOLLARS":null,
    "TOTAL_DAMAGE_DESCRIPTION":null,
    "TOTAL_HOUSES_DESTROYED":null,
    "TOTAL_HOUSES_DESTROYED_DESCRIPTION":null,
    "TOTAL_HOUSES_DAMAGED":null,
    "TOTAL_HOUSES_DAMAGED_DESCRIPTION":null
  },
  {
    "I_D":6978,
    "FLAG_TSUNAMI":"Tsu",
    "YEAR":1862,
    "MONTH":5,
    "DAY":27,
    "HOUR":null,
    "MINUTE":null,
    "SECOND":null,
    "FOCAL_DEPTH":null,
    "EQ_PRIMARY":5.9,
    "EQ_MAG_MW":null,
    "EQ_MAG_MS":null,
    "EQ_MAG_MB":null,
    "EQ_MAG_ML":5.9,
    "EQ_MAG_MFA":"",
    "EQ_MAG_UNK":null,
    "INTENSITY":7,
    "COUNTRY":"USA",
    "STATE":"CA",
    "LOCATION_NAME":"CALIFORNIA:  SAN DIEGO",
    "LATITUDE":"32.7",
    "LONGITUDE":"-117.2",
    "REGION_CODE":"150",
    "DEATHS":null,
    "DEATHS_DESCRIPTION":null,
    "MISSING":null,
    "MISSING_DESCRIPTION":"",
    "INJURIES":null,
    "INJURIES_DESCRIPTION":null,
    "DAMAGE_MILLIONS_DOLLARS":null,
    "DAMAGE_DESCRIPTION":null,
    "HOUSES_DESTROYED":null,
    "HOUSES_DESTROYED_DESCRIPTION":null,
    "HOUSES_DAMAGED":null,
    "HOUSES_DAMAGED_DESCRIPTION":null,
    "TOTAL_DEATHS":null,
    "TOTAL_DEATHS_DESCRIPTION":null,
    "TOTAL_MISSING":null,
    "TOTAL_MISSING_DESCRIPTION":"",
    "TOTAL_INJURIES":null,
    "TOTAL_INJURIES_DESCRIPTION":null,
    "TOTAL_DAMAGE_MILLIONS_DOLLARS":null,
    "TOTAL_DAMAGE_DESCRIPTION":null,
    "TOTAL_HOUSES_DESTROYED":null,
    "TOTAL_HOUSES_DESTROYED_DESCRIPTION":null,
    "TOTAL_HOUSES_DAMAGED":null,
    "TOTAL_HOUSES_DAMAGED_DESCRIPTION":null
  },
  {
    "I_D":2099,
    "FLAG_TSUNAMI":"Tsu",
    "YEAR":1865,
    "MONTH":10,
    "DAY":8,
    "HOUR":20,
    "MINUTE":46,
    "SECOND":null,
    "FOCAL_DEPTH":null,
    "EQ_PRIMARY":6.3,
    "EQ_MAG_MW":null,
    "EQ_MAG_MS":null,
    "EQ_MAG_MB":null,
    "EQ_MAG_ML":6.3,
    "EQ_MAG_MFA":"",
    "EQ_MAG_UNK":null,
    "INTENSITY":8,
    "COUNTRY":"USA",
    "STATE":"CA",
    "LOCATION_NAME":"CALIFORNIA:  SANTA CRUZ",
    "LATITUDE":"37.2",
    "LONGITUDE":"-121.9",
    "REGION_CODE":"150",
    "DEATHS":null,
    "DEATHS_DESCRIPTION":null,
    "MISSING":null,
    "MISSING_DESCRIPTION":"",
    "INJURIES":null,
    "INJURIES_DESCRIPTION":null,
    "DAMAGE_MILLIONS_DOLLARS":0.5,
    "DAMAGE_DESCRIPTION":1,
    "HOUSES_DESTROYED":null,
    "HOUSES_DESTROYED_DESCRIPTION":2,
    "HOUSES_DAMAGED":null,
    "HOUSES_DAMAGED_DESCRIPTION":null,
    "TOTAL_DEATHS":null,
    "TOTAL_DEATHS_DESCRIPTION":null,
    "TOTAL_MISSING":null,
    "TOTAL_MISSING_DESCRIPTION":"",
    "TOTAL_INJURIES":null,
    "TOTAL_INJURIES_DESCRIPTION":null,
    "TOTAL_DAMAGE_MILLIONS_DOLLARS":0.5,
    "TOTAL_DAMAGE_DESCRIPTION":1,
    "TOTAL_HOUSES_DESTROYED":null,
    "TOTAL_HOUSES_DESTROYED_DESCRIPTION":2,
    "TOTAL_HOUSES_DAMAGED":null,
    "TOTAL_HOUSES_DAMAGED_DESCRIPTION":null
  },
  {
    "I_D":2148,
    "FLAG_TSUNAMI":"Tsu",
    "YEAR":1868,
    "MONTH":10,
    "DAY":21,
    "HOUR":15,
    "MINUTE":53,
    "SECOND":    ,
    "FOCAL_DEPTH":null,
    "EQ_PRIMARY":6.8,
    "EQ_MAG_MW":null,
    "EQ_MAG_MS":null,
    "EQ_MAG_MB":null,
    "EQ_MAG_ML":6.8,
    "EQ_MAG_MFA":"",
    "EQ_MAG_UNK":null,
    "INTENSITY":9,
    "COUNTRY":"USA",
    "STATE":"CA",
    "LOCATION_NAME":"CALIFORNIA:  HAYWARD",
    "LATITUDE":"SAN FRANCISCO",
    "LONGITUDE":"37.7",
    "REGION_CODE":"-122.1",
    "DEATHS":150,
    "DEATHS_DESCRIPTION":30,
    "MISSING":1,
    "MISSING_DESCRIPTION":"",
    "INJURIES":null,
    "INJURIES_DESCRIPTION":null,
    "DAMAGE_MILLIONS_DOLLARS":null,
    "DAMAGE_DESCRIPTION":0.35,
    "HOUSES_DESTROYED":1,
    "HOUSES_DESTROYED_DESCRIPTION":null,
    "HOUSES_DAMAGED":2,
    "HOUSES_DAMAGED_DESCRIPTION":null,
    "TOTAL_DEATHS":null,
    "TOTAL_DEATHS_DESCRIPTION":30,
    "TOTAL_MISSING":1,
    "TOTAL_MISSING_DESCRIPTION":"",
    "TOTAL_INJURIES":null,
    "TOTAL_INJURIES_DESCRIPTION":null,
    "TOTAL_DAMAGE_MILLIONS_DOLLARS":null,
    "TOTAL_DAMAGE_DESCRIPTION":0.35,
    "TOTAL_HOUSES_DESTROYED":1,
    "TOTAL_HOUSES_DESTROYED_DESCRIPTION":null,
    "TOTAL_HOUSES_DAMAGED":3,
    "TOTAL_HOUSES_DAMAGED_DESCRIPTION":null
  },
  {
    "I_D":2180,
    "FLAG_TSUNAMI":"",
    "YEAR":1871,
    "MONTH":3,
    "DAY":2,
    "HOUR":21,
    "MINUTE":5,
    "SECOND":null,
    "FOCAL_DEPTH":null,
    "EQ_PRIMARY":5.9,
    "EQ_MAG_MW":null,
    "EQ_MAG_MS":null,
    "EQ_MAG_MB":null,
    "EQ_MAG_ML":5.9,
    "EQ_MAG_MFA":"",
    "EQ_MAG_UNK":null,
    "INTENSITY":7,
    "COUNTRY":"USA",
    "STATE":"CA",
    "LOCATION_NAME":"CALIFORNIA:  HUMBOLDT COUNTY",
    "LATITUDE":"40.4",
    "LONGITUDE":"-124.2",
    "REGION_CODE":"150",
    "DEATHS":null,
    "DEATHS_DESCRIPTION":null,
    "MISSING":null,
    "MISSING_DESCRIPTION":"",
    "INJURIES":null,
    "INJURIES_DESCRIPTION":null,
    "DAMAGE_MILLIONS_DOLLARS":null,
    "DAMAGE_DESCRIPTION":1,
    "HOUSES_DESTROYED":null,
    "HOUSES_DESTROYED_DESCRIPTION":null,
    "HOUSES_DAMAGED":null,
    "HOUSES_DAMAGED_DESCRIPTION":null,
    "TOTAL_DEATHS":null,
    "TOTAL_DEATHS_DESCRIPTION":null,
    "TOTAL_MISSING":null,
    "TOTAL_MISSING_DESCRIPTION":"",
    "TOTAL_INJURIES":null,
    "TOTAL_INJURIES_DESCRIPTION":null,
    "TOTAL_DAMAGE_MILLIONS_DOLLARS":null,
    "TOTAL_DAMAGE_DESCRIPTION":1,
    "TOTAL_HOUSES_DESTROYED":null,
    "TOTAL_HOUSES_DESTROYED_DESCRIPTION":null,
    "TOTAL_HOUSES_DAMAGED":null,
    "TOTAL_HOUSES_DAMAGED_DESCRIPTION":null
  },
  {
    "I_D":2195,
    "FLAG_TSUNAMI":"Tsu",
    "YEAR":1872,
    "MONTH":3,
    "DAY":26,
    "HOUR":10,
    "MINUTE":30,
    "SECOND":null,
    "FOCAL_DEPTH":null,
    "EQ_PRIMARY":7.8,
    "EQ_MAG_MW":7.8,
    "EQ_MAG_MS":null,
    "EQ_MAG_MB":null,
    "EQ_MAG_ML":7.3,
    "EQ_MAG_MFA":"",
    "EQ_MAG_UNK":null,
    "INTENSITY":10,
    "COUNTRY":"USA",
    "STATE":"CA",
    "LOCATION_NAME":"CALIFORNIA:  OWENS VALLEY",
    "LATITUDE":"36.7",
    "LONGITUDE":"-118.1",
    "REGION_CODE":"150",
    "DEATHS":27,
    "DEATHS_DESCRIPTION":1,
    "MISSING":null,
    "MISSING_DESCRIPTION":"",
    "INJURIES":56,
    "INJURIES_DESCRIPTION":2,
    "DAMAGE_MILLIONS_DOLLARS":0.25,
    "DAMAGE_DESCRIPTION":1,
    "HOUSES_DESTROYED":52,
    "HOUSES_DESTROYED_DESCRIPTION":2,
    "HOUSES_DAMAGED":null,
    "HOUSES_DAMAGED_DESCRIPTION":null,
    "TOTAL_DEATHS":27,
    "TOTAL_DEATHS_DESCRIPTION":1,
    "TOTAL_MISSING":null,
    "TOTAL_MISSING_DESCRIPTION":"",
    "TOTAL_INJURIES":56,
    "TOTAL_INJURIES_DESCRIPTION":2,
    "TOTAL_DAMAGE_MILLIONS_DOLLARS":0.25,
    "TOTAL_DAMAGE_DESCRIPTION":1,
    "TOTAL_HOUSES_DESTROYED":52,
    "TOTAL_HOUSES_DESTROYED_DESCRIPTION":2,
    "TOTAL_HOUSES_DAMAGED":null,
    "TOTAL_HOUSES_DAMAGED_DESCRIPTION":null
  },
  {
    "I_D":6179,
    "FLAG_TSUNAMI":"Tsu",
    "YEAR":1873,
    "MONTH":11,
    "DAY":23,
    "HOUR":5,
    "MINUTE":9,
    "SECOND":null,
    "FOCAL_DEPTH":null,
    "EQ_PRIMARY":6.7,
    "EQ_MAG_MW":null,
    "EQ_MAG_MS":null,
    "EQ_MAG_MB":null,
    "EQ_MAG_ML":6.7,
    "EQ_MAG_MFA":"",
    "EQ_MAG_UNK":null,
    "INTENSITY":8,
    "COUNTRY":"USA",
    "STATE":"CA",
    "LOCATION_NAME":"CALIFORNIA:  NORTHERN",
    "LATITUDE":"42",
    "LONGITUDE":"-124",
    "REGION_CODE":"150",
    "DEATHS":null,
    "DEATHS_DESCRIPTION":null,
    "MISSING":null,
    "MISSING_DESCRIPTION":"",
    "INJURIES":null,
    "INJURIES_DESCRIPTION":null,
    "DAMAGE_MILLIONS_DOLLARS":null,
    "DAMAGE_DESCRIPTION":1,
    "HOUSES_DESTROYED":null,
    "HOUSES_DESTROYED_DESCRIPTION":null,
    "HOUSES_DAMAGED":null,
    "HOUSES_DAMAGED_DESCRIPTION":null,
    "TOTAL_DEATHS":null,
    "TOTAL_DEATHS_DESCRIPTION":null,
    "TOTAL_MISSING":null,
    "TOTAL_MISSING_DESCRIPTION":"",
    "TOTAL_INJURIES":null,
    "TOTAL_INJURIES_DESCRIPTION":null,
    "TOTAL_DAMAGE_MILLIONS_DOLLARS":null,
    "TOTAL_DAMAGE_DESCRIPTION":1,
    "TOTAL_HOUSES_DESTROYED":null,
    "TOTAL_HOUSES_DESTROYED_DESCRIPTION":null,
    "TOTAL_HOUSES_DAMAGED":null,
    "TOTAL_HOUSES_DAMAGED_DESCRIPTION":null
  },
  {
    "I_D":2418,
    "FLAG_TSUNAMI":"",
    "YEAR":1892,
    "MONTH":4,
    "DAY":21,
    "HOUR":17,
    "MINUTE":43,
    "SECOND":null,
    "FOCAL_DEPTH":null,
    "EQ_PRIMARY":6.2,
    "EQ_MAG_MW":null,
    "EQ_MAG_MS":null,
    "EQ_MAG_MB":null,
    "EQ_MAG_ML":6.2,
    "EQ_MAG_MFA":"",
    "EQ_MAG_UNK":null,
    "INTENSITY":9,
    "COUNTRY":"USA",
    "STATE":"CA",
    "LOCATION_NAME":"CALIFORNIA:  WINTERS",
    "LATITUDE":"38.5",
    "LONGITUDE":"-121.9",
    "REGION_CODE":"150",
    "DEATHS":null,
    "DEATHS_DESCRIPTION":null,
    "MISSING":null,
    "MISSING_DESCRIPTION":"",
    "INJURIES":null,
    "INJURIES_DESCRIPTION":null,
    "DAMAGE_MILLIONS_DOLLARS":null,
    "DAMAGE_DESCRIPTION":2,
    "HOUSES_DESTROYED":null,
    "HOUSES_DESTROYED_DESCRIPTION":null,
    "HOUSES_DAMAGED":null,
    "HOUSES_DAMAGED_DESCRIPTION":null,
    "TOTAL_DEATHS":null,
    "TOTAL_DEATHS_DESCRIPTION":null,
    "TOTAL_MISSING":null,
    "TOTAL_MISSING_DESCRIPTION":"",
    "TOTAL_INJURIES":null,
    "TOTAL_INJURIES_DESCRIPTION":null,
    "TOTAL_DAMAGE_MILLIONS_DOLLARS":null,
    "TOTAL_DAMAGE_DESCRIPTION":2,
    "TOTAL_HOUSES_DESTROYED":null,
    "TOTAL_HOUSES_DESTROYED_DESCRIPTION":null,
    "TOTAL_HOUSES_DAMAGED":null,
    "TOTAL_HOUSES_DAMAGED_DESCRIPTION":null
  },
  {
    "I_D":2532,
    "FLAG_TSUNAMI":"Tsu",
    "YEAR":1898,
    "MONTH":3,
    "DAY":31,
    "HOUR":7,
    "MINUTE":43,
    "SECOND":null,
    "FOCAL_DEPTH":null,
    "EQ_PRIMARY":6.5,
    "EQ_MAG_MW":null,
    "EQ_MAG_MS":6.5,
    "EQ_MAG_MB":null,
    "EQ_MAG_ML":6.2,
    "EQ_MAG_MFA":"",
    "EQ_MAG_UNK":null,
    "INTENSITY":8,
    "COUNTRY":"USA",
    "STATE":"CA",
    "LOCATION_NAME":"CALIFORNIA:  SONOMA COUNTY",
    "LATITUDE":"38.2",
    "LONGITUDE":"-122.4",
    "REGION_CODE":"150",
    "DEATHS":null,
    "DEATHS_DESCRIPTION":null,
    "MISSING":null,
    "MISSING_DESCRIPTION":"",
    "INJURIES":null,
    "INJURIES_DESCRIPTION":null,
    "DAMAGE_MILLIONS_DOLLARS":null,
    "DAMAGE_DESCRIPTION":2,
    "HOUSES_DESTROYED":null,
    "HOUSES_DESTROYED_DESCRIPTION":null,
    "HOUSES_DAMAGED":null,
    "HOUSES_DAMAGED_DESCRIPTION":null,
    "TOTAL_DEATHS":null,
    "TOTAL_DEATHS_DESCRIPTION":null,
    "TOTAL_MISSING":null,
    "TOTAL_MISSING_DESCRIPTION":"",
    "TOTAL_INJURIES":null,
    "TOTAL_INJURIES_DESCRIPTION":null,
    "TOTAL_DAMAGE_MILLIONS_DOLLARS":null,
    "TOTAL_DAMAGE_DESCRIPTION":2,
    "TOTAL_HOUSES_DESTROYED":null,
    "TOTAL_HOUSES_DESTROYED_DESCRIPTION":null,
    "TOTAL_HOUSES_DAMAGED":null,
    "TOTAL_HOUSES_DAMAGED_DESCRIPTION":null
  },
  {
    "I_D":2564,
    "FLAG_TSUNAMI":"Tsu",
    "YEAR":1899,
    "MONTH":12,
    "DAY":25,
    "HOUR":12,
    "MINUTE":25,
    "SECOND":null,
    "FOCAL_DEPTH":null,
    "EQ_PRIMARY":6.4,
    "EQ_MAG_MW":null,
    "EQ_MAG_MS":6.4,
    "EQ_MAG_MB":null,
    "EQ_MAG_ML":6.6,
    "EQ_MAG_MFA":"",
    "EQ_MAG_UNK":null,
    "INTENSITY":9,
    "COUNTRY":"USA",
    "STATE":"CA",
    "LOCATION_NAME":"CALIFORNIA",
    "LATITUDE":"33.5",
    "LONGITUDE":"-117",
    "REGION_CODE":"150",
    "DEATHS":6,
    "DEATHS_DESCRIPTION":1,
    "MISSING":null,
    "MISSING_DESCRIPTION":"",
    "INJURIES":8,
    "INJURIES_DESCRIPTION":1,
    "DAMAGE_MILLIONS_DOLLARS":null,
    "DAMAGE_DESCRIPTION":2,
    "HOUSES_DESTROYED":null,
    "HOUSES_DESTROYED_DESCRIPTION":null,
    "HOUSES_DAMAGED":null,
    "HOUSES_DAMAGED_DESCRIPTION":null,
    "TOTAL_DEATHS":null,
    "TOTAL_DEATHS_DESCRIPTION":null,
    "TOTAL_MISSING":null,
    "TOTAL_MISSING_DESCRIPTION":"",
    "TOTAL_INJURIES":null,
    "TOTAL_INJURIES_DESCRIPTION":null,
    "TOTAL_DAMAGE_MILLIONS_DOLLARS":null,
    "TOTAL_DAMAGE_DESCRIPTION":null,
    "TOTAL_HOUSES_DESTROYED":null,
    "TOTAL_HOUSES_DESTROYED_DESCRIPTION":null,
    "TOTAL_HOUSES_DAMAGED":null,
    "TOTAL_HOUSES_DAMAGED_DESCRIPTION":null
  },
  {
    "I_D":7018,
    "FLAG_TSUNAMI":"Tsu",
    "YEAR":1901,
    "MONTH":3,
    "DAY":3,
    "HOUR":7,
    "MINUTE":45,
    "SECOND":null,
    "FOCAL_DEPTH":null,
    "EQ_PRIMARY":6.4,
    "EQ_MAG_MW":null,
    "EQ_MAG_MS":null,
    "EQ_MAG_MB":null,
    "EQ_MAG_ML":6.4,
    "EQ_MAG_MFA":"",
    "EQ_MAG_UNK":null,
    "INTENSITY":8,
    "COUNTRY":"USA",
    "STATE":"CA",
    "LOCATION_NAME":"CALIFORNIA:  SAN DIEGO",
    "LATITUDE":"36",
    "LONGITUDE":"-120.5",
    "REGION_CODE":"150",
    "DEATHS":null,
    "DEATHS_DESCRIPTION":null,
    "MISSING":null,
    "MISSING_DESCRIPTION":"",
    "INJURIES":null,
    "INJURIES_DESCRIPTION":null,
    "DAMAGE_MILLIONS_DOLLARS":null,
    "DAMAGE_DESCRIPTION":1,
    "HOUSES_DESTROYED":null,
    "HOUSES_DESTROYED_DESCRIPTION":null,
    "HOUSES_DAMAGED":null,
    "HOUSES_DAMAGED_DESCRIPTION":null,
    "TOTAL_DEATHS":null,
    "TOTAL_DEATHS_DESCRIPTION":null,
    "TOTAL_MISSING":null,
    "TOTAL_MISSING_DESCRIPTION":"",
    "TOTAL_INJURIES":null,
    "TOTAL_INJURIES_DESCRIPTION":null,
    "TOTAL_DAMAGE_MILLIONS_DOLLARS":null,
    "TOTAL_DAMAGE_DESCRIPTION":1,
    "TOTAL_HOUSES_DESTROYED":null,
    "TOTAL_HOUSES_DESTROYED_DESCRIPTION":null,
    "TOTAL_HOUSES_DAMAGED":null,
    "TOTAL_HOUSES_DAMAGED_DESCRIPTION":null
  },
  {
    "I_D":2768,
    "FLAG_TSUNAMI":"Tsu",
    "YEAR":1906,
    "MONTH":4,
    "DAY":18,
    "HOUR":13,
    "MINUTE":12,
    "SECOND":21,
    "FOCAL_DEPTH":20,
    "EQ_PRIMARY":7.9,
    "EQ_MAG_MW":7.9,
    "EQ_MAG_MS":7.8,
    "EQ_MAG_MB":null,
    "EQ_MAG_ML":null,
    "EQ_MAG_MFA":"",
    "EQ_MAG_UNK":8.3,
    "INTENSITY":11,
    "COUNTRY":"USA",
    "STATE":"CA",
    "LOCATION_NAME":"CALIFORNIA:  SAN FRANCISCO",
    "LATITUDE":"37.67",
    "LONGITUDE":"-122.48",
    "REGION_CODE":"150",
    "DEATHS":700,
    "DEATHS_DESCRIPTION":3,
    "MISSING":null,
    "MISSING_DESCRIPTION":"",
    "INJURIES":null,
    "INJURIES_DESCRIPTION":null,
    "DAMAGE_MILLIONS_DOLLARS":400,
    "DAMAGE_DESCRIPTION":4,
    "HOUSES_DESTROYED":28188,
    "HOUSES_DESTROYED_DESCRIPTION":4,
    "HOUSES_DAMAGED":null,
    "HOUSES_DAMAGED_DESCRIPTION":null,
    "TOTAL_DEATHS":null,
    "TOTAL_DEATHS_DESCRIPTION":null,
    "TOTAL_MISSING":null,
    "TOTAL_MISSING_DESCRIPTION":"",
    "TOTAL_INJURIES":null,
    "TOTAL_INJURIES_DESCRIPTION":null,
    "TOTAL_DAMAGE_MILLIONS_DOLLARS":null,
    "TOTAL_DAMAGE_DESCRIPTION":null,
    "TOTAL_HOUSES_DESTROYED":null,
    "TOTAL_HOUSES_DESTROYED_DESCRIPTION":null,
    "TOTAL_HOUSES_DAMAGED":null,
    "TOTAL_HOUSES_DAMAGED_DESCRIPTION":null
  },
  {
    "I_D":3033,
    "FLAG_TSUNAMI":"",
    "YEAR":1915,
    "MONTH":6,
    "DAY":23,
    "HOUR":4,
    "MINUTE":56,
    "SECOND":    ,
    "FOCAL_DEPTH":null,
    "EQ_PRIMARY":6.2,
    "EQ_MAG_MW":null,
    "EQ_MAG_MS":null,
    "EQ_MAG_MB":null,
    "EQ_MAG_ML":null,
    "EQ_MAG_MFA":"",
    "EQ_MAG_UNK":6.2,
    "INTENSITY":null,
    "COUNTRY":"USA",
    "STATE":"CA",
    "LOCATION_NAME":"CALIFORNIA:  EL CENTRO",
    "LATITUDE":"32.8",
    "LONGITUDE":"-115.5",
    "REGION_CODE":"150",
    "DEATHS":6,
    "DEATHS_DESCRIPTION":1,
    "MISSING":null,
    "MISSING_DESCRIPTION":"",
    "INJURIES":null,
    "INJURIES_DESCRIPTION":null,
    "DAMAGE_MILLIONS_DOLLARS":0.9,
    "DAMAGE_DESCRIPTION":1,
    "HOUSES_DESTROYED":null,
    "HOUSES_DESTROYED_DESCRIPTION":null,
    "HOUSES_DAMAGED":null,
    "HOUSES_DAMAGED_DESCRIPTION":null,
    "TOTAL_DEATHS":null,
    "TOTAL_DEATHS_DESCRIPTION":null,
    "TOTAL_MISSING":null,
    "TOTAL_MISSING_DESCRIPTION":"",
    "TOTAL_INJURIES":null,
    "TOTAL_INJURIES_DESCRIPTION":null,
    "TOTAL_DAMAGE_MILLIONS_DOLLARS":null,
    "TOTAL_DAMAGE_DESCRIPTION":null,
    "TOTAL_HOUSES_DESTROYED":null,
    "TOTAL_HOUSES_DESTROYED_DESCRIPTION":null,
    "TOTAL_HOUSES_DAMAGED":null,
    "TOTAL_HOUSES_DAMAGED_DESCRIPTION":null
  },
  {
    "I_D":3111,
    "FLAG_TSUNAMI":"",
    "YEAR":1918,
    "MONTH":4,
    "DAY":21,
    "HOUR":22,
    "MINUTE":32,
    "SECOND":    ,
    "FOCAL_DEPTH":null,
    "EQ_PRIMARY":6.8,
    "EQ_MAG_MW":null,
    "EQ_MAG_MS":null,
    "EQ_MAG_MB":null,
    "EQ_MAG_ML":null,
    "EQ_MAG_MFA":"",
    "EQ_MAG_UNK":6.8,
    "INTENSITY":null,
    "COUNTRY":"USA",
    "STATE":"CA",
    "LOCATION_NAME":"CALIFORNIA",
    "LATITUDE":"33.7",
    "LONGITUDE":"-117",
    "REGION_CODE":"150",
    "DEATHS":null,
    "DEATHS_DESCRIPTION":null,
    "MISSING":null,
    "MISSING_DESCRIPTION":"",
    "INJURIES":null,
    "INJURIES_DESCRIPTION":null,
    "DAMAGE_MILLIONS_DOLLARS":0.2,
    "DAMAGE_DESCRIPTION":1,
    "HOUSES_DESTROYED":null,
    "HOUSES_DESTROYED_DESCRIPTION":null,
    "HOUSES_DAMAGED":null,
    "HOUSES_DAMAGED_DESCRIPTION":null,
    "TOTAL_DEATHS":null,
    "TOTAL_DEATHS_DESCRIPTION":null,
    "TOTAL_MISSING":null,
    "TOTAL_MISSING_DESCRIPTION":"",
    "TOTAL_INJURIES":null,
    "TOTAL_INJURIES_DESCRIPTION":null,
    "TOTAL_DAMAGE_MILLIONS_DOLLARS":null,
    "TOTAL_DAMAGE_DESCRIPTION":null,
    "TOTAL_HOUSES_DESTROYED":null,
    "TOTAL_HOUSES_DESTROYED_DESCRIPTION":null,
    "TOTAL_HOUSES_DAMAGED":null,
    "TOTAL_HOUSES_DAMAGED_DESCRIPTION":null
  },
  {
    "I_D":3189,
    "FLAG_TSUNAMI":"",
    "YEAR":1922,
    "MONTH":1,
    "DAY":31,
    "HOUR":13,
    "MINUTE":17,
    "SECOND":    ,
    "FOCAL_DEPTH":null,
    "EQ_PRIMARY":7.6,
    "EQ_MAG_MW":null,
    "EQ_MAG_MS":null,
    "EQ_MAG_MB":null,
    "EQ_MAG_ML":null,
    "EQ_MAG_MFA":"",
    "EQ_MAG_UNK":7.6,
    "INTENSITY":null,
    "COUNTRY":"USA",
    "STATE":"CA",
    "LOCATION_NAME":"CALIFORNIA:  NORTHERN",
    "LATITUDE":"41",
    "LONGITUDE":"-125.5",
    "REGION_CODE":"150",
    "DEATHS":null,
    "DEATHS_DESCRIPTION":null,
    "MISSING":null,
    "MISSING_DESCRIPTION":"",
    "INJURIES":null,
    "INJURIES_DESCRIPTION":null,
    "DAMAGE_MILLIONS_DOLLARS":null,
    "DAMAGE_DESCRIPTION":1,
    "HOUSES_DESTROYED":null,
    "HOUSES_DESTROYED_DESCRIPTION":null,
    "HOUSES_DAMAGED":null,
    "HOUSES_DAMAGED_DESCRIPTION":null,
    "TOTAL_DEATHS":null,
    "TOTAL_DEATHS_DESCRIPTION":null,
    "TOTAL_MISSING":null,
    "TOTAL_MISSING_DESCRIPTION":"",
    "TOTAL_INJURIES":null,
    "TOTAL_INJURIES_DESCRIPTION":null,
    "TOTAL_DAMAGE_MILLIONS_DOLLARS":null,
    "TOTAL_DAMAGE_DESCRIPTION":null,
    "TOTAL_HOUSES_DESTROYED":null,
    "TOTAL_HOUSES_DESTROYED_DESCRIPTION":null,
    "TOTAL_HOUSES_DAMAGED":null,
    "TOTAL_HOUSES_DAMAGED_DESCRIPTION":null
  },
  {
    "I_D":6280,
    "FLAG_TSUNAMI":"Tsu",
    "YEAR":1923,
    "MONTH":1,
    "DAY":22,
    "HOUR":9,
    "MINUTE":4,
    "SECOND":18,
    "FOCAL_DEPTH":null,
    "EQ_PRIMARY":7.2,
    "EQ_MAG_MW":null,
    "EQ_MAG_MS":7.2,
    "EQ_MAG_MB":null,
    "EQ_MAG_ML":6.5,
    "EQ_MAG_MFA":"",
    "EQ_MAG_UNK":null,
    "INTENSITY":8,
    "COUNTRY":"USA",
    "STATE":"CA",
    "LOCATION_NAME":"CALIFORNIA:  NORTHERN",
    "LATITUDE":"40.8",
    "LONGITUDE":"-124.5",
    "REGION_CODE":"150",
    "DEATHS":null,
    "DEATHS_DESCRIPTION":null,
    "MISSING":null,
    "MISSING_DESCRIPTION":"",
    "INJURIES":null,
    "INJURIES_DESCRIPTION":null,
    "DAMAGE_MILLIONS_DOLLARS":null,
    "DAMAGE_DESCRIPTION":1,
    "HOUSES_DESTROYED":null,
    "HOUSES_DESTROYED_DESCRIPTION":null,
    "HOUSES_DAMAGED":null,
    "HOUSES_DAMAGED_DESCRIPTION":null,
    "TOTAL_DEATHS":null,
    "TOTAL_DEATHS_DESCRIPTION":null,
    "TOTAL_MISSING":null,
    "TOTAL_MISSING_DESCRIPTION":"",
    "TOTAL_INJURIES":null,
    "TOTAL_INJURIES_DESCRIPTION":null,
    "TOTAL_DAMAGE_MILLIONS_DOLLARS":null,
    "TOTAL_DAMAGE_DESCRIPTION":1,
    "TOTAL_HOUSES_DESTROYED":null,
    "TOTAL_HOUSES_DESTROYED_DESCRIPTION":null,
    "TOTAL_HOUSES_DAMAGED":null,
    "TOTAL_HOUSES_DAMAGED_DESCRIPTION":null
  },
  {
    "I_D":3270,
    "FLAG_TSUNAMI":"",
    "YEAR":1925,
    "MONTH":6,
    "DAY":29,
    "HOUR":14,
    "MINUTE":42,
    "SECOND":    ,
    "FOCAL_DEPTH":null,
    "EQ_PRIMARY":6.2,
    "EQ_MAG_MW":null,
    "EQ_MAG_MS":null,
    "EQ_MAG_MB":null,
    "EQ_MAG_ML":null,
    "EQ_MAG_MFA":"",
    "EQ_MAG_UNK":6.2,
    "INTENSITY":null,
    "COUNTRY":"USA",
    "STATE":"CA",
    "LOCATION_NAME":"CALIFORNIA:  SANTA BARBARA",
    "LATITUDE":"34.5",
    "LONGITUDE":"-119.6",
    "REGION_CODE":"150",
    "DEATHS":13,
    "DEATHS_DESCRIPTION":1,
    "MISSING":null,
    "MISSING_DESCRIPTION":"",
    "INJURIES":null,
    "INJURIES_DESCRIPTION":null,
    "DAMAGE_MILLIONS_DOLLARS":8,
    "DAMAGE_DESCRIPTION":3,
    "HOUSES_DESTROYED":null,
    "HOUSES_DESTROYED_DESCRIPTION":null,
    "HOUSES_DAMAGED":null,
    "HOUSES_DAMAGED_DESCRIPTION":null,
    "TOTAL_DEATHS":null,
    "TOTAL_DEATHS_DESCRIPTION":null,
    "TOTAL_MISSING":null,
    "TOTAL_MISSING_DESCRIPTION":"",
    "TOTAL_INJURIES":null,
    "TOTAL_INJURIES_DESCRIPTION":null,
    "TOTAL_DAMAGE_MILLIONS_DOLLARS":null,
    "TOTAL_DAMAGE_DESCRIPTION":null,
    "TOTAL_HOUSES_DESTROYED":null,
    "TOTAL_HOUSES_DESTROYED_DESCRIPTION":null,
    "TOTAL_HOUSES_DAMAGED":null,
    "TOTAL_HOUSES_DAMAGED_DESCRIPTION":null
  },
  {
    "I_D":3305,
    "FLAG_TSUNAMI":"Tsu",
    "YEAR":1927,
    "MONTH":1,
    "DAY":1,
    "HOUR":8,
    "MINUTE":16,
    "SECOND":    ,
    "FOCAL_DEPTH":null,
    "EQ_PRIMARY":5.8,
    "EQ_MAG_MW":null,
    "EQ_MAG_MS":null,
    "EQ_MAG_MB":null,
    "EQ_MAG_ML":null,
    "EQ_MAG_MFA":"",
    "EQ_MAG_UNK":5.8,
    "INTENSITY":null,
    "COUNTRY":"USA",
    "STATE":"CA",
    "LOCATION_NAME":"CALIFORNIA",
    "LATITUDE":" MEXICO",
    "LONGITUDE":"32.5",
    "REGION_CODE":"-115.5",
    "DEATHS":150,
    "DEATHS_DESCRIPTION":null,
    "MISSING":null,
    "MISSING_DESCRIPTION":"",
    "INJURIES":null,
    "INJURIES_DESCRIPTION":null,
    "DAMAGE_MILLIONS_DOLLARS":1,
    "DAMAGE_DESCRIPTION":1,
    "HOUSES_DESTROYED":2,
    "HOUSES_DESTROYED_DESCRIPTION":null,
    "HOUSES_DAMAGED":1,
    "HOUSES_DAMAGED_DESCRIPTION":20,
    "TOTAL_DEATHS":1,
    "TOTAL_DEATHS_DESCRIPTION":1,
    "TOTAL_MISSING":1,
    "TOTAL_MISSING_DESCRIPTION":"",
    "TOTAL_INJURIES":null,
    "TOTAL_INJURIES_DESCRIPTION":null,
    "TOTAL_DAMAGE_MILLIONS_DOLLARS":1,
    "TOTAL_DAMAGE_DESCRIPTION":3,
    "TOTAL_HOUSES_DESTROYED":2,
    "TOTAL_HOUSES_DESTROYED_DESCRIPTION":null,
    "TOTAL_HOUSES_DAMAGED":1,
    "TOTAL_HOUSES_DAMAGED_DESCRIPTION":20
  },
  {
    "I_D":3335,
    "FLAG_TSUNAMI":"Tsu",
    "YEAR":1927,
    "MONTH":11,
    "DAY":4,
    "HOUR":13,
    "MINUTE":50,
    "SECOND":43,
    "FOCAL_DEPTH":10,
    "EQ_PRIMARY":7.3,
    "EQ_MAG_MW":7.3,
    "EQ_MAG_MS":7.1,
    "EQ_MAG_MB":7.3,
    "EQ_MAG_ML":null,
    "EQ_MAG_MFA":"",
    "EQ_MAG_UNK":null,
    "INTENSITY":8,
    "COUNTRY":"USA",
    "STATE":"CA",
    "LOCATION_NAME":"CALIFORNIA:  S:  OFF COAST",
    "LATITUDE":"34.813",
    "LONGITUDE":"-120.774",
    "REGION_CODE":"150",
    "DEATHS":null,
    "DEATHS_DESCRIPTION":null,
    "MISSING":null,
    "MISSING_DESCRIPTION":"",
    "INJURIES":null,
    "INJURIES_DESCRIPTION":null,
    "DAMAGE_MILLIONS_DOLLARS":null,
    "DAMAGE_DESCRIPTION":2,
    "HOUSES_DESTROYED":null,
    "HOUSES_DESTROYED_DESCRIPTION":null,
    "HOUSES_DAMAGED":null,
    "HOUSES_DAMAGED_DESCRIPTION":null,
    "TOTAL_DEATHS":null,
    "TOTAL_DEATHS_DESCRIPTION":null,
    "TOTAL_MISSING":null,
    "TOTAL_MISSING_DESCRIPTION":"",
    "TOTAL_INJURIES":null,
    "TOTAL_INJURIES_DESCRIPTION":null,
    "TOTAL_DAMAGE_MILLIONS_DOLLARS":null,
    "TOTAL_DAMAGE_DESCRIPTION":2,
    "TOTAL_HOUSES_DESTROYED":null,
    "TOTAL_HOUSES_DESTROYED_DESCRIPTION":null,
    "TOTAL_HOUSES_DAMAGED":null,
    "TOTAL_HOUSES_DAMAGED_DESCRIPTION":null
  },
  {
    "I_D":6619,
    "FLAG_TSUNAMI":"Tsu",
    "YEAR":1930,
    "MONTH":8,
    "DAY":31,
    "HOUR":0,
    "MINUTE":40,
    "SECOND":38,
    "FOCAL_DEPTH":15,
    "EQ_PRIMARY":5.2,
    "EQ_MAG_MW":null,
    "EQ_MAG_MS":5.2,
    "EQ_MAG_MB":null,
    "EQ_MAG_ML":null,
    "EQ_MAG_MFA":"",
    "EQ_MAG_UNK":null,
    "INTENSITY":7,
    "COUNTRY":"USA",
    "STATE":"CA",
    "LOCATION_NAME":"CALIFORNIA:  SOUTHERN",
    "LATITUDE":"34.03",
    "LONGITUDE":"-118.643",
    "REGION_CODE":"150",
    "DEATHS":null,
    "DEATHS_DESCRIPTION":null,
    "MISSING":null,
    "MISSING_DESCRIPTION":"",
    "INJURIES":null,
    "INJURIES_DESCRIPTION":null,
    "DAMAGE_MILLIONS_DOLLARS":null,
    "DAMAGE_DESCRIPTION":1,
    "HOUSES_DESTROYED":null,
    "HOUSES_DESTROYED_DESCRIPTION":null,
    "HOUSES_DAMAGED":null,
    "HOUSES_DAMAGED_DESCRIPTION":null,
    "TOTAL_DEATHS":1,
    "TOTAL_DEATHS_DESCRIPTION":1,
    "TOTAL_MISSING":null,
    "TOTAL_MISSING_DESCRIPTION":"",
    "TOTAL_INJURIES":null,
    "TOTAL_INJURIES_DESCRIPTION":null,
    "TOTAL_DAMAGE_MILLIONS_DOLLARS":null,
    "TOTAL_DAMAGE_DESCRIPTION":1,
    "TOTAL_HOUSES_DESTROYED":null,
    "TOTAL_HOUSES_DESTROYED_DESCRIPTION":null,
    "TOTAL_HOUSES_DAMAGED":null,
    "TOTAL_HOUSES_DAMAGED_DESCRIPTION":null
  },
  {
    "I_D":3516,
    "FLAG_TSUNAMI":"Tsu",
    "YEAR":1933,
    "MONTH":3,
    "DAY":11,
    "HOUR":1,
    "MINUTE":54,
    "SECOND":7.8,
    "FOCAL_DEPTH":16,
    "EQ_PRIMARY":6.3,
    "EQ_MAG_MW":null,
    "EQ_MAG_MS":null,
    "EQ_MAG_MB":null,
    "EQ_MAG_ML":6.3,
    "EQ_MAG_MFA":"",
    "EQ_MAG_UNK":null,
    "INTENSITY":9,
    "COUNTRY":"USA",
    "STATE":"CA",
    "LOCATION_NAME":"CALIFORNIA:  LONG BEACH",
    "LATITUDE":"33.62",
    "LONGITUDE":"-117.97",
    "REGION_CODE":"150",
    "DEATHS":120,
    "DEATHS_DESCRIPTION":3,
    "MISSING":null,
    "MISSING_DESCRIPTION":"",
    "INJURIES":null,
    "INJURIES_DESCRIPTION":null,
    "DAMAGE_MILLIONS_DOLLARS":40,
    "DAMAGE_DESCRIPTION":4,
    "HOUSES_DESTROYED":null,
    "HOUSES_DESTROYED_DESCRIPTION":null,
    "HOUSES_DAMAGED":null,
    "HOUSES_DAMAGED_DESCRIPTION":null,
    "TOTAL_DEATHS":null,
    "TOTAL_DEATHS_DESCRIPTION":null,
    "TOTAL_MISSING":null,
    "TOTAL_MISSING_DESCRIPTION":"",
    "TOTAL_INJURIES":null,
    "TOTAL_INJURIES_DESCRIPTION":null,
    "TOTAL_DAMAGE_MILLIONS_DOLLARS":null,
    "TOTAL_DAMAGE_DESCRIPTION":null,
    "TOTAL_HOUSES_DESTROYED":null,
    "TOTAL_HOUSES_DESTROYED_DESCRIPTION":null,
    "TOTAL_HOUSES_DAMAGED":null,
    "TOTAL_HOUSES_DAMAGED_DESCRIPTION":null
  },
  {
    "I_D":3539,
    "FLAG_TSUNAMI":"",
    "YEAR":1934,
    "MONTH":12,
    "DAY":31,
    "HOUR":null,
    "MINUTE":null,
    "SECOND":    ,
    "FOCAL_DEPTH":null,
    "EQ_PRIMARY":7.1,
    "EQ_MAG_MW":null,
    "EQ_MAG_MS":null,
    "EQ_MAG_MB":null,
    "EQ_MAG_ML":null,
    "EQ_MAG_MFA":"",
    "EQ_MAG_UNK":7.1,
    "INTENSITY":10,
    "COUNTRY":"USA",
    "STATE":"CA",
    "LOCATION_NAME":"CALIFORNIA:  BAJA",
    "LATITUDE":"IMPERIAL VALLEY",
    "LONGITUDE":"31.8",
    "REGION_CODE":"-115.5",
    "DEATHS":150,
    "DEATHS_DESCRIPTION":null,
    "MISSING":null,
    "MISSING_DESCRIPTION":"",
    "INJURIES":null,
    "INJURIES_DESCRIPTION":null,
    "DAMAGE_MILLIONS_DOLLARS":null,
    "DAMAGE_DESCRIPTION":null,
    "HOUSES_DESTROYED":null,
    "HOUSES_DESTROYED_DESCRIPTION":null,
    "HOUSES_DAMAGED":null,
    "HOUSES_DAMAGED_DESCRIPTION":null,
    "TOTAL_DEATHS":null,
    "TOTAL_DEATHS_DESCRIPTION":null,
    "TOTAL_MISSING":null,
    "TOTAL_MISSING_DESCRIPTION":"",
    "TOTAL_INJURIES":null,
    "TOTAL_INJURIES_DESCRIPTION":null,
    "TOTAL_DAMAGE_MILLIONS_DOLLARS":null,
    "TOTAL_DAMAGE_DESCRIPTION":null,
    "TOTAL_HOUSES_DESTROYED":null,
    "TOTAL_HOUSES_DESTROYED_DESCRIPTION":null,
    "TOTAL_HOUSES_DAMAGED":null,
    "TOTAL_HOUSES_DAMAGED_DESCRIPTION":null
  },
  {
    "I_D":3662,
    "FLAG_TSUNAMI":"",
    "YEAR":1940,
    "MONTH":5,
    "DAY":19,
    "HOUR":4,
    "MINUTE":36,
    "SECOND":40.9,
    "FOCAL_DEPTH":16,
    "EQ_PRIMARY":7.2,
    "EQ_MAG_MW":null,
    "EQ_MAG_MS":7.2,
    "EQ_MAG_MB":6.9,
    "EQ_MAG_ML":6.4,
    "EQ_MAG_MFA":"",
    "EQ_MAG_UNK":null,
    "INTENSITY":10,
    "COUNTRY":"USA",
    "STATE":"CA",
    "LOCATION_NAME":"CALIFORNIA; MEXICO",
    "LATITUDE":"32.733",
    "LONGITUDE":"-115.5",
    "REGION_CODE":"150",
    "DEATHS":9,
    "DEATHS_DESCRIPTION":1,
    "MISSING":null,
    "MISSING_DESCRIPTION":"",
    "INJURIES":null,
    "INJURIES_DESCRIPTION":null,
    "DAMAGE_MILLIONS_DOLLARS":33,
    "DAMAGE_DESCRIPTION":4,
    "HOUSES_DESTROYED":null,
    "HOUSES_DESTROYED_DESCRIPTION":null,
    "HOUSES_DAMAGED":null,
    "HOUSES_DAMAGED_DESCRIPTION":null,
    "TOTAL_DEATHS":9,
    "TOTAL_DEATHS_DESCRIPTION":1,
    "TOTAL_MISSING":null,
    "TOTAL_MISSING_DESCRIPTION":"",
    "TOTAL_INJURIES":null,
    "TOTAL_INJURIES_DESCRIPTION":null,
    "TOTAL_DAMAGE_MILLIONS_DOLLARS":33,
    "TOTAL_DAMAGE_DESCRIPTION":4,
    "TOTAL_HOUSES_DESTROYED":null,
    "TOTAL_HOUSES_DESTROYED_DESCRIPTION":null,
    "TOTAL_HOUSES_DAMAGED":null,
    "TOTAL_HOUSES_DAMAGED_DESCRIPTION":null
  },
  {
    "I_D":6346,
    "FLAG_TSUNAMI":"Tsu",
    "YEAR":1941,
    "MONTH":2,
    "DAY":9,
    "HOUR":9,
    "MINUTE":44,
    "SECOND":4,
    "FOCAL_DEPTH":null,
    "EQ_PRIMARY":6.6,
    "EQ_MAG_MW":null,
    "EQ_MAG_MS":6.6,
    "EQ_MAG_MB":null,
    "EQ_MAG_ML":6.4,
    "EQ_MAG_MFA":"",
    "EQ_MAG_UNK":null,
    "INTENSITY":6,
    "COUNTRY":"USA",
    "STATE":"CA",
    "LOCATION_NAME":"CALIFORNIA:  NORTHERN",
    "LATITUDE":"40.5",
    "LONGITUDE":"-125.25",
    "REGION_CODE":"150",
    "DEATHS":null,
    "DEATHS_DESCRIPTION":null,
    "MISSING":null,
    "MISSING_DESCRIPTION":"",
    "INJURIES":null,
    "INJURIES_DESCRIPTION":null,
    "DAMAGE_MILLIONS_DOLLARS":null,
    "DAMAGE_DESCRIPTION":1,
    "HOUSES_DESTROYED":null,
    "HOUSES_DESTROYED_DESCRIPTION":null,
    "HOUSES_DAMAGED":null,
    "HOUSES_DAMAGED_DESCRIPTION":null,
    "TOTAL_DEATHS":null,
    "TOTAL_DEATHS_DESCRIPTION":null,
    "TOTAL_MISSING":null,
    "TOTAL_MISSING_DESCRIPTION":"",
    "TOTAL_INJURIES":null,
    "TOTAL_INJURIES_DESCRIPTION":null,
    "TOTAL_DAMAGE_MILLIONS_DOLLARS":null,
    "TOTAL_DAMAGE_DESCRIPTION":1,
    "TOTAL_HOUSES_DESTROYED":null,
    "TOTAL_HOUSES_DESTROYED_DESCRIPTION":null,
    "TOTAL_HOUSES_DAMAGED":null,
    "TOTAL_HOUSES_DAMAGED_DESCRIPTION":null
  },
  {
    "I_D":3852,
    "FLAG_TSUNAMI":"",
    "YEAR":1947,
    "MONTH":4,
    "DAY":10,
    "HOUR":15,
    "MINUTE":58,
    "SECOND":    ,
    "FOCAL_DEPTH":null,
    "EQ_PRIMARY":6.4,
    "EQ_MAG_MW":null,
    "EQ_MAG_MS":null,
    "EQ_MAG_MB":null,
    "EQ_MAG_ML":null,
    "EQ_MAG_MFA":"",
    "EQ_MAG_UNK":6.4,
    "INTENSITY":null,
    "COUNTRY":"USA",
    "STATE":"CA",
    "LOCATION_NAME":"CALIFORNIA",
    "LATITUDE":"35",
    "LONGITUDE":"-116.6",
    "REGION_CODE":"150",
    "DEATHS":null,
    "DEATHS_DESCRIPTION":null,
    "MISSING":null,
    "MISSING_DESCRIPTION":"",
    "INJURIES":null,
    "INJURIES_DESCRIPTION":null,
    "DAMAGE_MILLIONS_DOLLARS":null,
    "DAMAGE_DESCRIPTION":2,
    "HOUSES_DESTROYED":null,
    "HOUSES_DESTROYED_DESCRIPTION":null,
    "HOUSES_DAMAGED":null,
    "HOUSES_DAMAGED_DESCRIPTION":null,
    "TOTAL_DEATHS":null,
    "TOTAL_DEATHS_DESCRIPTION":null,
    "TOTAL_MISSING":null,
    "TOTAL_MISSING_DESCRIPTION":"",
    "TOTAL_INJURIES":null,
    "TOTAL_INJURIES_DESCRIPTION":null,
    "TOTAL_DAMAGE_MILLIONS_DOLLARS":null,
    "TOTAL_DAMAGE_DESCRIPTION":null,
    "TOTAL_HOUSES_DESTROYED":null,
    "TOTAL_HOUSES_DESTROYED_DESCRIPTION":null,
    "TOTAL_HOUSES_DAMAGED":null,
    "TOTAL_HOUSES_DAMAGED_DESCRIPTION":null
  },
  {
    "I_D":3999,
    "FLAG_TSUNAMI":"",
    "YEAR":1952,
    "MONTH":7,
    "DAY":21,
    "HOUR":11,
    "MINUTE":52,
    "SECOND":14,
    "FOCAL_DEPTH":16,
    "EQ_PRIMARY":7.7,
    "EQ_MAG_MW":null,
    "EQ_MAG_MS":7.7,
    "EQ_MAG_MB":7.3,
    "EQ_MAG_ML":7.2,
    "EQ_MAG_MFA":"",
    "EQ_MAG_UNK":7.7,
    "INTENSITY":11,
    "COUNTRY":"USA",
    "STATE":"CA",
    "LOCATION_NAME":"CALIFORNIA:  KERN COUNTY",
    "LATITUDE":"35",
    "LONGITUDE":"-119.017",
    "REGION_CODE":"150",
    "DEATHS":12,
    "DEATHS_DESCRIPTION":1,
    "MISSING":null,
    "MISSING_DESCRIPTION":"",
    "INJURIES":null,
    "INJURIES_DESCRIPTION":null,
    "DAMAGE_MILLIONS_DOLLARS":60,
    "DAMAGE_DESCRIPTION":4,
    "HOUSES_DESTROYED":null,
    "HOUSES_DESTROYED_DESCRIPTION":null,
    "HOUSES_DAMAGED":null,
    "HOUSES_DAMAGED_DESCRIPTION":null,
    "TOTAL_DEATHS":null,
    "TOTAL_DEATHS_DESCRIPTION":null,
    "TOTAL_MISSING":null,
    "TOTAL_MISSING_DESCRIPTION":"",
    "TOTAL_INJURIES":null,
    "TOTAL_INJURIES_DESCRIPTION":null,
    "TOTAL_DAMAGE_MILLIONS_DOLLARS":null,
    "TOTAL_DAMAGE_DESCRIPTION":null,
    "TOTAL_HOUSES_DESTROYED":null,
    "TOTAL_HOUSES_DESTROYED_DESCRIPTION":null,
    "TOTAL_HOUSES_DAMAGED":null,
    "TOTAL_HOUSES_DAMAGED_DESCRIPTION":null
  },
  {
    "I_D":4002,
    "FLAG_TSUNAMI":"",
    "YEAR":1952,
    "MONTH":8,
    "DAY":22,
    "HOUR":22,
    "MINUTE":41,
    "SECOND":24,
    "FOCAL_DEPTH":16,
    "EQ_PRIMARY":5.8,
    "EQ_MAG_MW":null,
    "EQ_MAG_MS":null,
    "EQ_MAG_MB":null,
    "EQ_MAG_ML":5.8,
    "EQ_MAG_MFA":"",
    "EQ_MAG_UNK":null,
    "INTENSITY":8,
    "COUNTRY":"USA",
    "STATE":"CA",
    "LOCATION_NAME":"CALIFORNIA:  KERN COUNTY",
    "LATITUDE":"35.333",
    "LONGITUDE":"-118.917",
    "REGION_CODE":"150",
    "DEATHS":2,
    "DEATHS_DESCRIPTION":1,
    "MISSING":null,
    "MISSING_DESCRIPTION":"",
    "INJURIES":null,
    "INJURIES_DESCRIPTION":2,
    "DAMAGE_MILLIONS_DOLLARS":10,
    "DAMAGE_DESCRIPTION":3,
    "HOUSES_DESTROYED":90,
    "HOUSES_DESTROYED_DESCRIPTION":2,
    "HOUSES_DAMAGED":null,
    "HOUSES_DAMAGED_DESCRIPTION":null,
    "TOTAL_DEATHS":2,
    "TOTAL_DEATHS_DESCRIPTION":1,
    "TOTAL_MISSING":null,
    "TOTAL_MISSING_DESCRIPTION":"",
    "TOTAL_INJURIES":null,
    "TOTAL_INJURIES_DESCRIPTION":null,
    "TOTAL_DAMAGE_MILLIONS_DOLLARS":10,
    "TOTAL_DAMAGE_DESCRIPTION":3,
    "TOTAL_HOUSES_DESTROYED":90,
    "TOTAL_HOUSES_DESTROYED_DESCRIPTION":2,
    "TOTAL_HOUSES_DAMAGED":null,
    "TOTAL_HOUSES_DAMAGED_DESCRIPTION":null
  },
  {
    "I_D":4502,
    "FLAG_TSUNAMI":"",
    "YEAR":1969,
    "MONTH":10,
    "DAY":2,
    "HOUR":4,
    "MINUTE":56,
    "SECOND":46.5,
    "FOCAL_DEPTH":10,
    "EQ_PRIMARY":4.8,
    "EQ_MAG_MW":null,
    "EQ_MAG_MS":4.8,
    "EQ_MAG_MB":5.2,
    "EQ_MAG_ML":5.6,
    "EQ_MAG_MFA":"",
    "EQ_MAG_UNK":null,
    "INTENSITY":8,
    "COUNTRY":"USA",
    "STATE":"CA",
    "LOCATION_NAME":"CALIFORNIA:  SANTA ROSA",
    "LATITUDE":"38.467",
    "LONGITUDE":"-122.692",
    "REGION_CODE":"150",
    "DEATHS":1,
    "DEATHS_DESCRIPTION":1,
    "MISSING":null,
    "MISSING_DESCRIPTION":"",
    "INJURIES":null,
    "INJURIES_DESCRIPTION":null,
    "DAMAGE_MILLIONS_DOLLARS":8.35,
    "DAMAGE_DESCRIPTION":3,
    "HOUSES_DESTROYED":null,
    "HOUSES_DESTROYED_DESCRIPTION":null,
    "HOUSES_DAMAGED":null,
    "HOUSES_DAMAGED_DESCRIPTION":null,
    "TOTAL_DEATHS":1,
    "TOTAL_DEATHS_DESCRIPTION":1,
    "TOTAL_MISSING":null,
    "TOTAL_MISSING_DESCRIPTION":"",
    "TOTAL_INJURIES":null,
    "TOTAL_INJURIES_DESCRIPTION":null,
    "TOTAL_DAMAGE_MILLIONS_DOLLARS":8.35,
    "TOTAL_DAMAGE_DESCRIPTION":3,
    "TOTAL_HOUSES_DESTROYED":null,
    "TOTAL_HOUSES_DESTROYED_DESCRIPTION":null,
    "TOTAL_HOUSES_DAMAGED":null,
    "TOTAL_HOUSES_DAMAGED_DESCRIPTION":null
  },
  {
    "I_D":4558,
    "FLAG_TSUNAMI":"",
    "YEAR":1971,
    "MONTH":2,
    "DAY":9,
    "HOUR":14,
    "MINUTE":0,
    "SECOND":41.8,
    "FOCAL_DEPTH":8,
    "EQ_PRIMARY":6.5,
    "EQ_MAG_MW":null,
    "EQ_MAG_MS":6.5,
    "EQ_MAG_MB":6.2,
    "EQ_MAG_ML":6.4,
    "EQ_MAG_MFA":"",
    "EQ_MAG_UNK":null,
    "INTENSITY":11,
    "COUNTRY":"USA",
    "STATE":"CA",
    "LOCATION_NAME":"CALIFORNIA:  SAN FERNANDO",
    "LATITUDE":"34.412",
    "LONGITUDE":"-118.4",
    "REGION_CODE":"150",
    "DEATHS":65,
    "DEATHS_DESCRIPTION":2,
    "MISSING":null,
    "MISSING_DESCRIPTION":"",
    "INJURIES":2000,
    "INJURIES_DESCRIPTION":4,
    "DAMAGE_MILLIONS_DOLLARS":505,
    "DAMAGE_DESCRIPTION":4,
    "HOUSES_DESTROYED":null,
    "HOUSES_DESTROYED_DESCRIPTION":null,
    "HOUSES_DAMAGED":null,
    "HOUSES_DAMAGED_DESCRIPTION":null,
    "TOTAL_DEATHS":65,
    "TOTAL_DEATHS_DESCRIPTION":2,
    "TOTAL_MISSING":null,
    "TOTAL_MISSING_DESCRIPTION":"",
    "TOTAL_INJURIES":2000,
    "TOTAL_INJURIES_DESCRIPTION":4,
    "TOTAL_DAMAGE_MILLIONS_DOLLARS":505,
    "TOTAL_DAMAGE_DESCRIPTION":4,
    "TOTAL_HOUSES_DESTROYED":null,
    "TOTAL_HOUSES_DESTROYED_DESCRIPTION":null,
    "TOTAL_HOUSES_DAMAGED":null,
    "TOTAL_HOUSES_DAMAGED_DESCRIPTION":null
  },
  {
    "I_D":4626,
    "FLAG_TSUNAMI":"",
    "YEAR":1973,
    "MONTH":2,
    "DAY":21,
    "HOUR":14,
    "MINUTE":45,
    "SECOND":57.3,
    "FOCAL_DEPTH":8,
    "EQ_PRIMARY":5.7,
    "EQ_MAG_MW":null,
    "EQ_MAG_MS":5.7,
    "EQ_MAG_MB":5.7,
    "EQ_MAG_ML":5.9,
    "EQ_MAG_MFA":"",
    "EQ_MAG_UNK":null,
    "INTENSITY":7,
    "COUNTRY":"USA",
    "STATE":"CA",
    "LOCATION_NAME":"CALIFORNIA:  OXNARD",
    "LATITUDE":"34.1",
    "LONGITUDE":"-119",
    "REGION_CODE":"150",
    "DEATHS":null,
    "DEATHS_DESCRIPTION":null,
    "MISSING":null,
    "MISSING_DESCRIPTION":"",
    "INJURIES":null,
    "INJURIES_DESCRIPTION":null,
    "DAMAGE_MILLIONS_DOLLARS":1,
    "DAMAGE_DESCRIPTION":2,
    "HOUSES_DESTROYED":null,
    "HOUSES_DESTROYED_DESCRIPTION":null,
    "HOUSES_DAMAGED":null,
    "HOUSES_DAMAGED_DESCRIPTION":null,
    "TOTAL_DEATHS":null,
    "TOTAL_DEATHS_DESCRIPTION":null,
    "TOTAL_MISSING":null,
    "TOTAL_MISSING_DESCRIPTION":"",
    "TOTAL_INJURIES":null,
    "TOTAL_INJURIES_DESCRIPTION":null,
    "TOTAL_DAMAGE_MILLIONS_DOLLARS":null,
    "TOTAL_DAMAGE_DESCRIPTION":null,
    "TOTAL_HOUSES_DESTROYED":null,
    "TOTAL_HOUSES_DESTROYED_DESCRIPTION":null,
    "TOTAL_HOUSES_DAMAGED":null,
    "TOTAL_HOUSES_DAMAGED_DESCRIPTION":null
  },
  {
    "I_D":4696,
    "FLAG_TSUNAMI":"",
    "YEAR":1975,
    "MONTH":8,
    "DAY":1,
    "HOUR":20,
    "MINUTE":20,
    "SECOND":12.9,
    "FOCAL_DEPTH":15,
    "EQ_PRIMARY":5.6,
    "EQ_MAG_MW":null,
    "EQ_MAG_MS":5.6,
    "EQ_MAG_MB":5.8,
    "EQ_MAG_ML":5.7,
    "EQ_MAG_MFA":"",
    "EQ_MAG_UNK":null,
    "INTENSITY":8,
    "COUNTRY":"USA",
    "STATE":"CA",
    "LOCATION_NAME":"CALIFORNIA:  OROVILLE",
    "LATITUDE":"39.439",
    "LONGITUDE":"-121.528",
    "REGION_CODE":"150",
    "DEATHS":null,
    "DEATHS_DESCRIPTION":null,
    "MISSING":null,
    "MISSING_DESCRIPTION":"",
    "INJURIES":10,
    "INJURIES_DESCRIPTION":1,
    "DAMAGE_MILLIONS_DOLLARS":3,
    "DAMAGE_DESCRIPTION":2,
    "HOUSES_DESTROYED":null,
    "HOUSES_DESTROYED_DESCRIPTION":null,
    "HOUSES_DAMAGED":null,
    "HOUSES_DAMAGED_DESCRIPTION":null,
    "TOTAL_DEATHS":null,
    "TOTAL_DEATHS_DESCRIPTION":null,
    "TOTAL_MISSING":null,
    "TOTAL_MISSING_DESCRIPTION":"",
    "TOTAL_INJURIES":10,
    "TOTAL_INJURIES_DESCRIPTION":1,
    "TOTAL_DAMAGE_MILLIONS_DOLLARS":3,
    "TOTAL_DAMAGE_DESCRIPTION":2,
    "TOTAL_HOUSES_DESTROYED":null,
    "TOTAL_HOUSES_DESTROYED_DESCRIPTION":null,
    "TOTAL_HOUSES_DAMAGED":null,
    "TOTAL_HOUSES_DAMAGED_DESCRIPTION":null
  },
  {
    "I_D":4813,
    "FLAG_TSUNAMI":"",
    "YEAR":1978,
    "MONTH":8,
    "DAY":13,
    "HOUR":22,
    "MINUTE":54,
    "SECOND":53.5,
    "FOCAL_DEPTH":7,
    "EQ_PRIMARY":5.6,
    "EQ_MAG_MW":null,
    "EQ_MAG_MS":5.6,
    "EQ_MAG_MB":5.5,
    "EQ_MAG_ML":5.7,
    "EQ_MAG_MFA":"",
    "EQ_MAG_UNK":5.6,
    "INTENSITY":7,
    "COUNTRY":"USA",
    "STATE":"CA",
    "LOCATION_NAME":"CALIFORNIA:  SOUTHERN",
    "LATITUDE":"34.35",
    "LONGITUDE":"-119.7",
    "REGION_CODE":"150",
    "DEATHS":null,
    "DEATHS_DESCRIPTION":null,
    "MISSING":null,
    "MISSING_DESCRIPTION":"",
    "INJURIES":65,
    "INJURIES_DESCRIPTION":2,
    "DAMAGE_MILLIONS_DOLLARS":15,
    "DAMAGE_DESCRIPTION":3,
    "HOUSES_DESTROYED":null,
    "HOUSES_DESTROYED_DESCRIPTION":null,
    "HOUSES_DAMAGED":null,
    "HOUSES_DAMAGED_DESCRIPTION":null,
    "TOTAL_DEATHS":null,
    "TOTAL_DEATHS_DESCRIPTION":null,
    "TOTAL_MISSING":null,
    "TOTAL_MISSING_DESCRIPTION":"",
    "TOTAL_INJURIES":null,
    "TOTAL_INJURIES_DESCRIPTION":null,
    "TOTAL_DAMAGE_MILLIONS_DOLLARS":null,
    "TOTAL_DAMAGE_DESCRIPTION":null,
    "TOTAL_HOUSES_DESTROYED":null,
    "TOTAL_HOUSES_DESTROYED_DESCRIPTION":null,
    "TOTAL_HOUSES_DAMAGED":null,
    "TOTAL_HOUSES_DAMAGED_DESCRIPTION":null
  },
  {
    "I_D":4847,
    "FLAG_TSUNAMI":"",
    "YEAR":1979,
    "MONTH":10,
    "DAY":15,
    "HOUR":23,
    "MINUTE":16,
    "SECOND":54.1,
    "FOCAL_DEPTH":10,
    "EQ_PRIMARY":6.9,
    "EQ_MAG_MW":null,
    "EQ_MAG_MS":6.9,
    "EQ_MAG_MB":5.7,
    "EQ_MAG_ML":6.4,
    "EQ_MAG_MFA":"",
    "EQ_MAG_UNK":null,
    "INTENSITY":9,
    "COUNTRY":"USA",
    "STATE":"CA",
    "LOCATION_NAME":"CALIFORNIA:  IMPERIAL VALLEY; MEXICO: MEXICALI",
    "LATITUDE":"32.634",
    "LONGITUDE":"-115.324",
    "REGION_CODE":"150",
    "DEATHS":null,
    "DEATHS_DESCRIPTION":null,
    "MISSING":null,
    "MISSING_DESCRIPTION":"",
    "INJURIES":91,
    "INJURIES_DESCRIPTION":2,
    "DAMAGE_MILLIONS_DOLLARS":30,
    "DAMAGE_DESCRIPTION":4,
    "HOUSES_DESTROYED":null,
    "HOUSES_DESTROYED_DESCRIPTION":null,
    "HOUSES_DAMAGED":null,
    "HOUSES_DAMAGED_DESCRIPTION":null,
    "TOTAL_DEATHS":null,
    "TOTAL_DEATHS_DESCRIPTION":null,
    "TOTAL_MISSING":null,
    "TOTAL_MISSING_DESCRIPTION":"",
    "TOTAL_INJURIES":null,
    "TOTAL_INJURIES_DESCRIPTION":null,
    "TOTAL_DAMAGE_MILLIONS_DOLLARS":null,
    "TOTAL_DAMAGE_DESCRIPTION":null,
    "TOTAL_HOUSES_DESTROYED":null,
    "TOTAL_HOUSES_DESTROYED_DESCRIPTION":null,
    "TOTAL_HOUSES_DAMAGED":null,
    "TOTAL_HOUSES_DAMAGED_DESCRIPTION":null
  },
  {
    "I_D":4870,
    "FLAG_TSUNAMI":"",
    "YEAR":1980,
    "MONTH":1,
    "DAY":24,
    "HOUR":19,
    "MINUTE":0,
    "SECOND":9.5,
    "FOCAL_DEPTH":11,
    "EQ_PRIMARY":5.9,
    "EQ_MAG_MW":null,
    "EQ_MAG_MS":5.9,
    "EQ_MAG_MB":5.3,
    "EQ_MAG_ML":5.8,
    "EQ_MAG_MFA":"",
    "EQ_MAG_UNK":null,
    "INTENSITY":7,
    "COUNTRY":"USA",
    "STATE":"CA",
    "LOCATION_NAME":"CALIFORNIA:  LIVERMORE",
    "LATITUDE":"37.855",
    "LONGITUDE":"-121.816",
    "REGION_CODE":"150",
    "DEATHS":null,
    "DEATHS_DESCRIPTION":null,
    "MISSING":null,
    "MISSING_DESCRIPTION":"",
    "INJURIES":50,
    "INJURIES_DESCRIPTION":1,
    "DAMAGE_MILLIONS_DOLLARS":11.5,
    "DAMAGE_DESCRIPTION":3,
    "HOUSES_DESTROYED":null,
    "HOUSES_DESTROYED_DESCRIPTION":null,
    "HOUSES_DAMAGED":null,
    "HOUSES_DAMAGED_DESCRIPTION":null,
    "TOTAL_DEATHS":null,
    "TOTAL_DEATHS_DESCRIPTION":null,
    "TOTAL_MISSING":null,
    "TOTAL_MISSING_DESCRIPTION":"",
    "TOTAL_INJURIES":50,
    "TOTAL_INJURIES_DESCRIPTION":1,
    "TOTAL_DAMAGE_MILLIONS_DOLLARS":11.5,
    "TOTAL_DAMAGE_DESCRIPTION":3,
    "TOTAL_HOUSES_DESTROYED":null,
    "TOTAL_HOUSES_DESTROYED_DESCRIPTION":null,
    "TOTAL_HOUSES_DAMAGED":null,
    "TOTAL_HOUSES_DAMAGED_DESCRIPTION":null
  },
  {
    "I_D":4878,
    "FLAG_TSUNAMI":"",
    "YEAR":1980,
    "MONTH":5,
    "DAY":25,
    "HOUR":16,
    "MINUTE":33,
    "SECOND":44.7,
    "FOCAL_DEPTH":7,
    "EQ_PRIMARY":6.1,
    "EQ_MAG_MW":null,
    "EQ_MAG_MS":6.1,
    "EQ_MAG_MB":6.1,
    "EQ_MAG_ML":null,
    "EQ_MAG_MFA":"",
    "EQ_MAG_UNK":null,
    "INTENSITY":7,
    "COUNTRY":"USA",
    "STATE":"CA",
    "LOCATION_NAME":"CALIFORNIA:  MAMMOTH LAKES",
    "LATITUDE":"37.6",
    "LONGITUDE":"-118.84",
    "REGION_CODE":"150",
    "DEATHS":null,
    "DEATHS_DESCRIPTION":null,
    "MISSING":null,
    "MISSING_DESCRIPTION":"",
    "INJURIES":7,
    "INJURIES_DESCRIPTION":1,
    "DAMAGE_MILLIONS_DOLLARS":2,
    "DAMAGE_DESCRIPTION":2,
    "HOUSES_DESTROYED":null,
    "HOUSES_DESTROYED_DESCRIPTION":null,
    "HOUSES_DAMAGED":null,
    "HOUSES_DAMAGED_DESCRIPTION":null,
    "TOTAL_DEATHS":null,
    "TOTAL_DEATHS_DESCRIPTION":null,
    "TOTAL_MISSING":null,
    "TOTAL_MISSING_DESCRIPTION":"",
    "TOTAL_INJURIES":7,
    "TOTAL_INJURIES_DESCRIPTION":1,
    "TOTAL_DAMAGE_MILLIONS_DOLLARS":2,
    "TOTAL_DAMAGE_DESCRIPTION":2,
    "TOTAL_HOUSES_DESTROYED":null,
    "TOTAL_HOUSES_DESTROYED_DESCRIPTION":null,
    "TOTAL_HOUSES_DAMAGED":null,
    "TOTAL_HOUSES_DAMAGED_DESCRIPTION":null
  },
  {
    "I_D":4901,
    "FLAG_TSUNAMI":"",
    "YEAR":1980,
    "MONTH":11,
    "DAY":8,
    "HOUR":10,
    "MINUTE":27,
    "SECOND":34,
    "FOCAL_DEPTH":19,
    "EQ_PRIMARY":7.2,
    "EQ_MAG_MW":null,
    "EQ_MAG_MS":7.2,
    "EQ_MAG_MB":6.2,
    "EQ_MAG_ML":null,
    "EQ_MAG_MFA":"",
    "EQ_MAG_UNK":null,
    "INTENSITY":7,
    "COUNTRY":"USA",
    "STATE":"CA",
    "LOCATION_NAME":"CALIFORNIA:  NORTH COAST",
    "LATITUDE":"41.117",
    "LONGITUDE":"-124.253",
    "REGION_CODE":"150",
    "DEATHS":5,
    "DEATHS_DESCRIPTION":1,
    "MISSING":null,
    "MISSING_DESCRIPTION":"",
    "INJURIES":null,
    "INJURIES_DESCRIPTION":null,
    "DAMAGE_MILLIONS_DOLLARS":2.75,
    "DAMAGE_DESCRIPTION":2,
    "HOUSES_DESTROYED":null,
    "HOUSES_DESTROYED_DESCRIPTION":null,
    "HOUSES_DAMAGED":null,
    "HOUSES_DAMAGED_DESCRIPTION":null,
    "TOTAL_DEATHS":null,
    "TOTAL_DEATHS_DESCRIPTION":null,
    "TOTAL_MISSING":null,
    "TOTAL_MISSING_DESCRIPTION":"",
    "TOTAL_INJURIES":null,
    "TOTAL_INJURIES_DESCRIPTION":null,
    "TOTAL_DAMAGE_MILLIONS_DOLLARS":null,
    "TOTAL_DAMAGE_DESCRIPTION":null,
    "TOTAL_HOUSES_DESTROYED":null,
    "TOTAL_HOUSES_DESTROYED_DESCRIPTION":null,
    "TOTAL_HOUSES_DAMAGED":null,
    "TOTAL_HOUSES_DAMAGED_DESCRIPTION":null
  },
  {
    "I_D":4919,
    "FLAG_TSUNAMI":"",
    "YEAR":1981,
    "MONTH":4,
    "DAY":26,
    "HOUR":12,
    "MINUTE":9,
    "SECOND":28.4,
    "FOCAL_DEPTH":6,
    "EQ_PRIMARY":6,
    "EQ_MAG_MW":null,
    "EQ_MAG_MS":6,
    "EQ_MAG_MB":5.5,
    "EQ_MAG_ML":null,
    "EQ_MAG_MFA":"",
    "EQ_MAG_UNK":null,
    "INTENSITY":7,
    "COUNTRY":"USA",
    "STATE":"CA",
    "LOCATION_NAME":"CALIFORNIA:  WESTMORLAND",
    "LATITUDE":"CALIPATRIA",
    "LONGITUDE":"33.133",
    "REGION_CODE":"-115.65",
    "DEATHS":150,
    "DEATHS_DESCRIPTION":null,
    "MISSING":null,
    "MISSING_DESCRIPTION":"",
    "INJURIES":null,
    "INJURIES_DESCRIPTION":null,
    "DAMAGE_MILLIONS_DOLLARS":null,
    "DAMAGE_DESCRIPTION":1.5,
    "HOUSES_DESTROYED":2,
    "HOUSES_DESTROYED_DESCRIPTION":null,
    "HOUSES_DAMAGED":null,
    "HOUSES_DAMAGED_DESCRIPTION":null,
    "TOTAL_DEATHS":null,
    "TOTAL_DEATHS_DESCRIPTION":null,
    "TOTAL_MISSING":null,
    "TOTAL_MISSING_DESCRIPTION":"",
    "TOTAL_INJURIES":null,
    "TOTAL_INJURIES_DESCRIPTION":null,
    "TOTAL_DAMAGE_MILLIONS_DOLLARS":null,
    "TOTAL_DAMAGE_DESCRIPTION":1.5,
    "TOTAL_HOUSES_DESTROYED":2,
    "TOTAL_HOUSES_DESTROYED_DESCRIPTION":null,
    "TOTAL_HOUSES_DAMAGED":null,
    "TOTAL_HOUSES_DAMAGED_DESCRIPTION":null
  },
  {
    "I_D":4977,
    "FLAG_TSUNAMI":"",
    "YEAR":1983,
    "MONTH":5,
    "DAY":2,
    "HOUR":23,
    "MINUTE":42,
    "SECOND":37.7,
    "FOCAL_DEPTH":10,
    "EQ_PRIMARY":6.2,
    "EQ_MAG_MW":null,
    "EQ_MAG_MS":6.2,
    "EQ_MAG_MB":6.2,
    "EQ_MAG_ML":null,
    "EQ_MAG_MFA":"",
    "EQ_MAG_UNK":null,
    "INTENSITY":8,
    "COUNTRY":"USA",
    "STATE":"CA",
    "LOCATION_NAME":"CALIFORNIA:  CENTRAL",
    "LATITUDE":" COALINGA",
    "LONGITUDE":"36.219",
    "REGION_CODE":"-120.317",
    "DEATHS":150,
    "DEATHS_DESCRIPTION":null,
    "MISSING":null,
    "MISSING_DESCRIPTION":"",
    "INJURIES":null,
    "INJURIES_DESCRIPTION":45,
    "DAMAGE_MILLIONS_DOLLARS":1,
    "DAMAGE_DESCRIPTION":31,
    "HOUSES_DESTROYED":4,
    "HOUSES_DESTROYED_DESCRIPTION":500,
    "HOUSES_DAMAGED":3,
    "HOUSES_DAMAGED_DESCRIPTION":null,
    "TOTAL_DEATHS":null,
    "TOTAL_DEATHS_DESCRIPTION":null,
    "TOTAL_MISSING":null,
    "TOTAL_MISSING_DESCRIPTION":"",
    "TOTAL_INJURIES":null,
    "TOTAL_INJURIES_DESCRIPTION":45,
    "TOTAL_DAMAGE_MILLIONS_DOLLARS":1,
    "TOTAL_DAMAGE_DESCRIPTION":31,
    "TOTAL_HOUSES_DESTROYED":4,
    "TOTAL_HOUSES_DESTROYED_DESCRIPTION":500,
    "TOTAL_HOUSES_DAMAGED":3,
    "TOTAL_HOUSES_DAMAGED_DESCRIPTION":null
  },
  {
    "I_D":5030,
    "FLAG_TSUNAMI":"",
    "YEAR":1984,
    "MONTH":4,
    "DAY":24,
    "HOUR":21,
    "MINUTE":15,
    "SECOND":19,
    "FOCAL_DEPTH":8,
    "EQ_PRIMARY":6.1,
    "EQ_MAG_MW":null,
    "EQ_MAG_MS":6.1,
    "EQ_MAG_MB":5.7,
    "EQ_MAG_ML":6.2,
    "EQ_MAG_MFA":"",
    "EQ_MAG_UNK":null,
    "INTENSITY":8,
    "COUNTRY":"USA",
    "STATE":"CA",
    "LOCATION_NAME":"CALIFORNIA:  CENTRAL:  MORGAN HILL",
    "LATITUDE":"37.32",
    "LONGITUDE":"-121.698",
    "REGION_CODE":"150",
    "DEATHS":null,
    "DEATHS_DESCRIPTION":null,
    "MISSING":null,
    "MISSING_DESCRIPTION":"",
    "INJURIES":27,
    "INJURIES_DESCRIPTION":1,
    "DAMAGE_MILLIONS_DOLLARS":8,
    "DAMAGE_DESCRIPTION":3,
    "HOUSES_DESTROYED":null,
    "HOUSES_DESTROYED_DESCRIPTION":null,
    "HOUSES_DAMAGED":null,
    "HOUSES_DAMAGED_DESCRIPTION":null,
    "TOTAL_DEATHS":null,
    "TOTAL_DEATHS_DESCRIPTION":null,
    "TOTAL_MISSING":null,
    "TOTAL_MISSING_DESCRIPTION":"",
    "TOTAL_INJURIES":27,
    "TOTAL_INJURIES_DESCRIPTION":1,
    "TOTAL_DAMAGE_MILLIONS_DOLLARS":8,
    "TOTAL_DAMAGE_DESCRIPTION":3,
    "TOTAL_HOUSES_DESTROYED":null,
    "TOTAL_HOUSES_DESTROYED_DESCRIPTION":null,
    "TOTAL_HOUSES_DAMAGED":null,
    "TOTAL_HOUSES_DAMAGED_DESCRIPTION":null
  },
  {
    "I_D":5100,
    "FLAG_TSUNAMI":"",
    "YEAR":1986,
    "MONTH":7,
    "DAY":8,
    "HOUR":9,
    "MINUTE":20,
    "SECOND":44.5,
    "FOCAL_DEPTH":12,
    "EQ_PRIMARY":6,
    "EQ_MAG_MW":null,
    "EQ_MAG_MS":6,
    "EQ_MAG_MB":5.8,
    "EQ_MAG_ML":null,
    "EQ_MAG_MFA":"",
    "EQ_MAG_UNK":null,
    "INTENSITY":7,
    "COUNTRY":"USA",
    "STATE":"CA",
    "LOCATION_NAME":"CALIFORNIA:  PALM SPRINGS",
    "LATITUDE":"34",
    "LONGITUDE":"-116.61",
    "REGION_CODE":"150",
    "DEATHS":null,
    "DEATHS_DESCRIPTION":null,
    "MISSING":null,
    "MISSING_DESCRIPTION":"",
    "INJURIES":29,
    "INJURIES_DESCRIPTION":1,
    "DAMAGE_MILLIONS_DOLLARS":4.5,
    "DAMAGE_DESCRIPTION":2,
    "HOUSES_DESTROYED":null,
    "HOUSES_DESTROYED_DESCRIPTION":null,
    "HOUSES_DAMAGED":null,
    "HOUSES_DAMAGED_DESCRIPTION":null,
    "TOTAL_DEATHS":null,
    "TOTAL_DEATHS_DESCRIPTION":null,
    "TOTAL_MISSING":null,
    "TOTAL_MISSING_DESCRIPTION":"",
    "TOTAL_INJURIES":29,
    "TOTAL_INJURIES_DESCRIPTION":1,
    "TOTAL_DAMAGE_MILLIONS_DOLLARS":4.5,
    "TOTAL_DAMAGE_DESCRIPTION":2,
    "TOTAL_HOUSES_DESTROYED":null,
    "TOTAL_HOUSES_DESTROYED_DESCRIPTION":null,
    "TOTAL_HOUSES_DAMAGED":null,
    "TOTAL_HOUSES_DAMAGED_DESCRIPTION":null
  },
  {
    "I_D":5102,
    "FLAG_TSUNAMI":"",
    "YEAR":1986,
    "MONTH":7,
    "DAY":13,
    "HOUR":13,
    "MINUTE":47,
    "SECOND":8.2,
    "FOCAL_DEPTH":6,
    "EQ_PRIMARY":5.8,
    "EQ_MAG_MW":null,
    "EQ_MAG_MS":5.8,
    "EQ_MAG_MB":5.6,
    "EQ_MAG_ML":5.3,
    "EQ_MAG_MFA":"",
    "EQ_MAG_UNK":null,
    "INTENSITY":6,
    "COUNTRY":"USA",
    "STATE":"CA",
    "LOCATION_NAME":"CALIFORNIA:  SAN DIEGO",
    "LATITUDE":" NEWPORT BEACH",
    "LONGITUDE":"32.97",
    "REGION_CODE":"-117.869",
    "DEATHS":150,
    "DEATHS_DESCRIPTION":null,
    "MISSING":null,
    "MISSING_DESCRIPTION":"",
    "INJURIES":null,
    "INJURIES_DESCRIPTION":null,
    "DAMAGE_MILLIONS_DOLLARS":null,
    "DAMAGE_DESCRIPTION":0.7,
    "HOUSES_DESTROYED":1,
    "HOUSES_DESTROYED_DESCRIPTION":null,
    "HOUSES_DAMAGED":null,
    "HOUSES_DAMAGED_DESCRIPTION":null,
    "TOTAL_DEATHS":null,
    "TOTAL_DEATHS_DESCRIPTION":null,
    "TOTAL_MISSING":null,
    "TOTAL_MISSING_DESCRIPTION":"",
    "TOTAL_INJURIES":null,
    "TOTAL_INJURIES_DESCRIPTION":null,
    "TOTAL_DAMAGE_MILLIONS_DOLLARS":null,
    "TOTAL_DAMAGE_DESCRIPTION":0.7,
    "TOTAL_HOUSES_DESTROYED":1,
    "TOTAL_HOUSES_DESTROYED_DESCRIPTION":null,
    "TOTAL_HOUSES_DAMAGED":null,
    "TOTAL_HOUSES_DAMAGED_DESCRIPTION":null
  },
  {
    "I_D":5105,
    "FLAG_TSUNAMI":"",
    "YEAR":1986,
    "MONTH":7,
    "DAY":21,
    "HOUR":14,
    "MINUTE":42,
    "SECOND":26.6,
    "FOCAL_DEPTH":9,
    "EQ_PRIMARY":6.2,
    "EQ_MAG_MW":null,
    "EQ_MAG_MS":6.2,
    "EQ_MAG_MB":6,
    "EQ_MAG_ML":null,
    "EQ_MAG_MFA":"",
    "EQ_MAG_UNK":null,
    "INTENSITY":6,
    "COUNTRY":"USA",
    "STATE":"CA",
    "LOCATION_NAME":"CALIFORNIA-NEVADA:  CHALFANT VALLEY",
    "LATITUDE":"37.537",
    "LONGITUDE":"-118.447",
    "REGION_CODE":"150",
    "DEATHS":null,
    "DEATHS_DESCRIPTION":null,
    "MISSING":null,
    "MISSING_DESCRIPTION":"",
    "INJURIES":null,
    "INJURIES_DESCRIPTION":null,
    "DAMAGE_MILLIONS_DOLLARS":1,
    "DAMAGE_DESCRIPTION":2,
    "HOUSES_DESTROYED":null,
    "HOUSES_DESTROYED_DESCRIPTION":null,
    "HOUSES_DAMAGED":null,
    "HOUSES_DAMAGED_DESCRIPTION":null,
    "TOTAL_DEATHS":null,
    "TOTAL_DEATHS_DESCRIPTION":null,
    "TOTAL_MISSING":null,
    "TOTAL_MISSING_DESCRIPTION":"",
    "TOTAL_INJURIES":null,
    "TOTAL_INJURIES_DESCRIPTION":null,
    "TOTAL_DAMAGE_MILLIONS_DOLLARS":1,
    "TOTAL_DAMAGE_DESCRIPTION":2,
    "TOTAL_HOUSES_DESTROYED":null,
    "TOTAL_HOUSES_DESTROYED_DESCRIPTION":null,
    "TOTAL_HOUSES_DAMAGED":null,
    "TOTAL_HOUSES_DAMAGED_DESCRIPTION":null
  },
  {
    "I_D":5143,
    "FLAG_TSUNAMI":"",
    "YEAR":1987,
    "MONTH":10,
    "DAY":1,
    "HOUR":14,
    "MINUTE":42,
    "SECOND":20,
    "FOCAL_DEPTH":10,
    "EQ_PRIMARY":5.7,
    "EQ_MAG_MW":null,
    "EQ_MAG_MS":5.7,
    "EQ_MAG_MB":5.8,
    "EQ_MAG_ML":5.9,
    "EQ_MAG_MFA":"",
    "EQ_MAG_UNK":null,
    "INTENSITY":8,
    "COUNTRY":"USA",
    "STATE":"CA",
    "LOCATION_NAME":"CALIFORNIA:  WHITTIER",
    "LATITUDE":"34.061",
    "LONGITUDE":"-118.078",
    "REGION_CODE":"150",
    "DEATHS":8,
    "DEATHS_DESCRIPTION":1,
    "MISSING":null,
    "MISSING_DESCRIPTION":"",
    "INJURIES":200,
    "INJURIES_DESCRIPTION":3,
    "DAMAGE_MILLIONS_DOLLARS":358,
    "DAMAGE_DESCRIPTION":4,
    "HOUSES_DESTROYED":null,
    "HOUSES_DESTROYED_DESCRIPTION":null,
    "HOUSES_DAMAGED":null,
    "HOUSES_DAMAGED_DESCRIPTION":null,
    "TOTAL_DEATHS":8,
    "TOTAL_DEATHS_DESCRIPTION":1,
    "TOTAL_MISSING":null,
    "TOTAL_MISSING_DESCRIPTION":"",
    "TOTAL_INJURIES":200,
    "TOTAL_INJURIES_DESCRIPTION":3,
    "TOTAL_DAMAGE_MILLIONS_DOLLARS":358,
    "TOTAL_DAMAGE_DESCRIPTION":4,
    "TOTAL_HOUSES_DESTROYED":null,
    "TOTAL_HOUSES_DESTROYED_DESCRIPTION":null,
    "TOTAL_HOUSES_DAMAGED":null,
    "TOTAL_HOUSES_DAMAGED_DESCRIPTION":null
  },
  {
    "I_D":5146,
    "FLAG_TSUNAMI":"",
    "YEAR":1987,
    "MONTH":10,
    "DAY":4,
    "HOUR":10,
    "MINUTE":59,
    "SECOND":38.1,
    "FOCAL_DEPTH":8,
    "EQ_PRIMARY":4.8,
    "EQ_MAG_MW":null,
    "EQ_MAG_MS":4.8,
    "EQ_MAG_MB":5.2,
    "EQ_MAG_ML":null,
    "EQ_MAG_MFA":"",
    "EQ_MAG_UNK":null,
    "INTENSITY":null,
    "COUNTRY":"USA",
    "STATE":"CA",
    "LOCATION_NAME":"CALIFORNIA:  WHITTIER",
    "LATITUDE":" PASADENA",
    "LONGITUDE":"34.07",
    "REGION_CODE":"-118.1",
    "DEATHS":150,
    "DEATHS_DESCRIPTION":1,
    "MISSING":1,
    "MISSING_DESCRIPTION":"",
    "INJURIES":null,
    "INJURIES_DESCRIPTION":null,
    "DAMAGE_MILLIONS_DOLLARS":2,
    "DAMAGE_DESCRIPTION":null,
    "HOUSES_DESTROYED":2,
    "HOUSES_DESTROYED_DESCRIPTION":null,
    "HOUSES_DAMAGED":null,
    "HOUSES_DAMAGED_DESCRIPTION":null,
    "TOTAL_DEATHS":null,
    "TOTAL_DEATHS_DESCRIPTION":1,
    "TOTAL_MISSING":1,
    "TOTAL_MISSING_DESCRIPTION":"",
    "TOTAL_INJURIES":null,
    "TOTAL_INJURIES_DESCRIPTION":null,
    "TOTAL_DAMAGE_MILLIONS_DOLLARS":2,
    "TOTAL_DAMAGE_DESCRIPTION":null,
    "TOTAL_HOUSES_DESTROYED":2,
    "TOTAL_HOUSES_DESTROYED_DESCRIPTION":null,
    "TOTAL_HOUSES_DAMAGED":null,
    "TOTAL_HOUSES_DAMAGED_DESCRIPTION":null
  },
  {
    "I_D":5148,
    "FLAG_TSUNAMI":"",
    "YEAR":1987,
    "MONTH":11,
    "DAY":24,
    "HOUR":1,
    "MINUTE":54,
    "SECOND":14.5,
    "FOCAL_DEPTH":5,
    "EQ_PRIMARY":6.2,
    "EQ_MAG_MW":null,
    "EQ_MAG_MS":6.2,
    "EQ_MAG_MB":5.7,
    "EQ_MAG_ML":null,
    "EQ_MAG_MFA":"",
    "EQ_MAG_UNK":null,
    "INTENSITY":6,
    "COUNTRY":"USA",
    "STATE":"CA",
    "LOCATION_NAME":"CALIFORNIA:  SUPERSTITION HILLS",
    "LATITUDE":"33.082",
    "LONGITUDE":"-115.775",
    "REGION_CODE":"150",
    "DEATHS":2,
    "DEATHS_DESCRIPTION":1,
    "MISSING":null,
    "MISSING_DESCRIPTION":"",
    "INJURIES":null,
    "INJURIES_DESCRIPTION":null,
    "DAMAGE_MILLIONS_DOLLARS":3,
    "DAMAGE_DESCRIPTION":2,
    "HOUSES_DESTROYED":null,
    "HOUSES_DESTROYED_DESCRIPTION":null,
    "HOUSES_DAMAGED":null,
    "HOUSES_DAMAGED_DESCRIPTION":null,
    "TOTAL_DEATHS":2,
    "TOTAL_DEATHS_DESCRIPTION":1,
    "TOTAL_MISSING":null,
    "TOTAL_MISSING_DESCRIPTION":"",
    "TOTAL_INJURIES":null,
    "TOTAL_INJURIES_DESCRIPTION":null,
    "TOTAL_DAMAGE_MILLIONS_DOLLARS":3,
    "TOTAL_DAMAGE_DESCRIPTION":2,
    "TOTAL_HOUSES_DESTROYED":null,
    "TOTAL_HOUSES_DESTROYED_DESCRIPTION":null,
    "TOTAL_HOUSES_DAMAGED":null,
    "TOTAL_HOUSES_DAMAGED_DESCRIPTION":null
  },
  {
    "I_D":5213,
    "FLAG_TSUNAMI":"Tsu",
    "YEAR":1989,
    "MONTH":10,
    "DAY":18,
    "HOUR":0,
    "MINUTE":4,
    "SECOND":15.2,
    "FOCAL_DEPTH":19,
    "EQ_PRIMARY":6.9,
    "EQ_MAG_MW":6.9,
    "EQ_MAG_MS":7.1,
    "EQ_MAG_MB":6.5,
    "EQ_MAG_ML":null,
    "EQ_MAG_MFA":"",
    "EQ_MAG_UNK":null,
    "INTENSITY":9,
    "COUNTRY":"USA",
    "STATE":"CA",
    "LOCATION_NAME":"CALIFORNIA:  LOMA PRIETA",
    "LATITUDE":"37.036",
    "LONGITUDE":"-121.883",
    "REGION_CODE":"150",
    "DEATHS":62,
    "DEATHS_DESCRIPTION":2,
    "MISSING":null,
    "MISSING_DESCRIPTION":"",
    "INJURIES":3757,
    "INJURIES_DESCRIPTION":4,
    "DAMAGE_MILLIONS_DOLLARS":5600,
    "DAMAGE_DESCRIPTION":4,
    "HOUSES_DESTROYED":null,
    "HOUSES_DESTROYED_DESCRIPTION":3,
    "HOUSES_DAMAGED":null,
    "HOUSES_DAMAGED_DESCRIPTION":null,
    "TOTAL_DEATHS":62,
    "TOTAL_DEATHS_DESCRIPTION":2,
    "TOTAL_MISSING":null,
    "TOTAL_MISSING_DESCRIPTION":"",
    "TOTAL_INJURIES":3757,
    "TOTAL_INJURIES_DESCRIPTION":4,
    "TOTAL_DAMAGE_MILLIONS_DOLLARS":5600,
    "TOTAL_DAMAGE_DESCRIPTION":4,
    "TOTAL_HOUSES_DESTROYED":null,
    "TOTAL_HOUSES_DESTROYED_DESCRIPTION":3,
    "TOTAL_HOUSES_DAMAGED":null,
    "TOTAL_HOUSES_DAMAGED_DESCRIPTION":null
  },
  {
    "I_D":5223,
    "FLAG_TSUNAMI":"",
    "YEAR":1990,
    "MONTH":2,
    "DAY":28,
    "HOUR":23,
    "MINUTE":43,
    "SECOND":36.6,
    "FOCAL_DEPTH":5,
    "EQ_PRIMARY":5.5,
    "EQ_MAG_MW":null,
    "EQ_MAG_MS":5.5,
    "EQ_MAG_MB":5.5,
    "EQ_MAG_ML":null,
    "EQ_MAG_MFA":"",
    "EQ_MAG_UNK":null,
    "INTENSITY":7,
    "COUNTRY":"USA",
    "STATE":"CA",
    "LOCATION_NAME":"CALIFORNIA:  S",
    "LATITUDE":"  CLAREMONT",
    "LONGITUDE":"  COVINA",
    "REGION_CODE":"34.14",
    "DEATHS":-117.7,
    "DEATHS_DESCRIPTION":150,
    "MISSING":null,
    "MISSING_DESCRIPTION":"",
    "INJURIES":null,
    "INJURIES_DESCRIPTION":null,
    "DAMAGE_MILLIONS_DOLLARS":30,
    "DAMAGE_DESCRIPTION":1,
    "HOUSES_DESTROYED":12.7,
    "HOUSES_DESTROYED_DESCRIPTION":3,
    "HOUSES_DAMAGED":null,
    "HOUSES_DAMAGED_DESCRIPTION":null,
    "TOTAL_DEATHS":null,
    "TOTAL_DEATHS_DESCRIPTION":null,
    "TOTAL_MISSING":null,
    "TOTAL_MISSING_DESCRIPTION":"",
    "TOTAL_INJURIES":null,
    "TOTAL_INJURIES_DESCRIPTION":null,
    "TOTAL_DAMAGE_MILLIONS_DOLLARS":30,
    "TOTAL_DAMAGE_DESCRIPTION":1,
    "TOTAL_HOUSES_DESTROYED":12.7,
    "TOTAL_HOUSES_DESTROYED_DESCRIPTION":3,
    "TOTAL_HOUSES_DAMAGED":null,
    "TOTAL_HOUSES_DAMAGED_DESCRIPTION":null
  },
  {
    "I_D":5295,
    "FLAG_TSUNAMI":"",
    "YEAR":1991,
    "MONTH":6,
    "DAY":28,
    "HOUR":14,
    "MINUTE":43,
    "SECOND":54.5,
    "FOCAL_DEPTH":11,
    "EQ_PRIMARY":5.1,
    "EQ_MAG_MW":null,
    "EQ_MAG_MS":5.1,
    "EQ_MAG_MB":5.8,
    "EQ_MAG_ML":null,
    "EQ_MAG_MFA":"",
    "EQ_MAG_UNK":null,
    "INTENSITY":7,
    "COUNTRY":"USA",
    "STATE":"CA",
    "LOCATION_NAME":"CALIFORNIA:  ARCADIA",
    "LATITUDE":" GLENDALE",
    "LONGITUDE":" LOS ANGELES",
    "REGION_CODE":"34.262",
    "DEATHS":-118.002,
    "DEATHS_DESCRIPTION":150,
    "MISSING":2,
    "MISSING_DESCRIPTION":"1",
    "INJURIES":null,
    "INJURIES_DESCRIPTION":null,
    "DAMAGE_MILLIONS_DOLLARS":104,
    "DAMAGE_DESCRIPTION":3,
    "HOUSES_DESTROYED":33.5,
    "HOUSES_DESTROYED_DESCRIPTION":4,
    "HOUSES_DAMAGED":null,
    "HOUSES_DAMAGED_DESCRIPTION":null,
    "TOTAL_DEATHS":null,
    "TOTAL_DEATHS_DESCRIPTION":null,
    "TOTAL_MISSING":2,
    "TOTAL_MISSING_DESCRIPTION":"1",
    "TOTAL_INJURIES":null,
    "TOTAL_INJURIES_DESCRIPTION":null,
    "TOTAL_DAMAGE_MILLIONS_DOLLARS":104,
    "TOTAL_DAMAGE_DESCRIPTION":3,
    "TOTAL_HOUSES_DESTROYED":33.5,
    "TOTAL_HOUSES_DESTROYED_DESCRIPTION":4,
    "TOTAL_HOUSES_DAMAGED":null,
    "TOTAL_HOUSES_DAMAGED_DESCRIPTION":null
  },
  {
    "I_D":5304,
    "FLAG_TSUNAMI":"",
    "YEAR":1991,
    "MONTH":8,
    "DAY":17,
    "HOUR":19,
    "MINUTE":29,
    "SECOND":40,
    "FOCAL_DEPTH":12,
    "EQ_PRIMARY":6.2,
    "EQ_MAG_MW":null,
    "EQ_MAG_MS":6.2,
    "EQ_MAG_MB":6,
    "EQ_MAG_ML":null,
    "EQ_MAG_MFA":"",
    "EQ_MAG_UNK":null,
    "INTENSITY":7,
    "COUNTRY":"USA",
    "STATE":"CA",
    "LOCATION_NAME":"CALIFORNIA:  HONEYDEW",
    "LATITUDE":" WHITETHORN",
    "LONGITUDE":" PETROLIA",
    "REGION_CODE":"40.235",
    "DEATHS":-124.348,
    "DEATHS_DESCRIPTION":150,
    "MISSING":null,
    "MISSING_DESCRIPTION":"",
    "INJURIES":null,
    "INJURIES_DESCRIPTION":null,
    "DAMAGE_MILLIONS_DOLLARS":null,
    "DAMAGE_DESCRIPTION":null,
    "HOUSES_DESTROYED":null,
    "HOUSES_DESTROYED_DESCRIPTION":2,
    "HOUSES_DAMAGED":null,
    "HOUSES_DAMAGED_DESCRIPTION":null,
    "TOTAL_DEATHS":null,
    "TOTAL_DEATHS_DESCRIPTION":null,
    "TOTAL_MISSING":null,
    "TOTAL_MISSING_DESCRIPTION":"",
    "TOTAL_INJURIES":null,
    "TOTAL_INJURIES_DESCRIPTION":null,
    "TOTAL_DAMAGE_MILLIONS_DOLLARS":null,
    "TOTAL_DAMAGE_DESCRIPTION":null,
    "TOTAL_HOUSES_DESTROYED":null,
    "TOTAL_HOUSES_DESTROYED_DESCRIPTION":2,
    "TOTAL_HOUSES_DAMAGED":null,
    "TOTAL_HOUSES_DAMAGED_DESCRIPTION":null
  },
  {
    "I_D":5320,
    "FLAG_TSUNAMI":"",
    "YEAR":1992,
    "MONTH":4,
    "DAY":23,
    "HOUR":4,
    "MINUTE":50,
    "SECOND":23.2,
    "FOCAL_DEPTH":12,
    "EQ_PRIMARY":6.3,
    "EQ_MAG_MW":null,
    "EQ_MAG_MS":6.3,
    "EQ_MAG_MB":5.7,
    "EQ_MAG_ML":6.1,
    "EQ_MAG_MFA":"",
    "EQ_MAG_UNK":null,
    "INTENSITY":7,
    "COUNTRY":"USA",
    "STATE":"CA",
    "LOCATION_NAME":"CALIFORNIA:  JOSHUA TREE",
    "LATITUDE":" ANGELUS OAKS",
    "LONGITUDE":"33.961",
    "REGION_CODE":"-116.318",
    "DEATHS":150,
    "DEATHS_DESCRIPTION":null,
    "MISSING":null,
    "MISSING_DESCRIPTION":"",
    "INJURIES":null,
    "INJURIES_DESCRIPTION":32,
    "DAMAGE_MILLIONS_DOLLARS":1,
    "DAMAGE_DESCRIPTION":null,
    "HOUSES_DESTROYED":2,
    "HOUSES_DESTROYED_DESCRIPTION":null,
    "HOUSES_DAMAGED":null,
    "HOUSES_DAMAGED_DESCRIPTION":null,
    "TOTAL_DEATHS":null,
    "TOTAL_DEATHS_DESCRIPTION":null,
    "TOTAL_MISSING":null,
    "TOTAL_MISSING_DESCRIPTION":"",
    "TOTAL_INJURIES":null,
    "TOTAL_INJURIES_DESCRIPTION":32,
    "TOTAL_DAMAGE_MILLIONS_DOLLARS":1,
    "TOTAL_DAMAGE_DESCRIPTION":null,
    "TOTAL_HOUSES_DESTROYED":2,
    "TOTAL_HOUSES_DESTROYED_DESCRIPTION":null,
    "TOTAL_HOUSES_DAMAGED":null,
    "TOTAL_HOUSES_DAMAGED_DESCRIPTION":null
  },
  {
    "I_D":5321,
    "FLAG_TSUNAMI":"Tsu",
    "YEAR":1992,
    "MONTH":4,
    "DAY":25,
    "HOUR":18,
    "MINUTE":6,
    "SECOND":4.2,
    "FOCAL_DEPTH":15,
    "EQ_PRIMARY":7.1,
    "EQ_MAG_MW":null,
    "EQ_MAG_MS":7.1,
    "EQ_MAG_MB":6.3,
    "EQ_MAG_ML":null,
    "EQ_MAG_MFA":"",
    "EQ_MAG_UNK":null,
    "INTENSITY":8,
    "COUNTRY":"USA",
    "STATE":"CA",
    "LOCATION_NAME":"CALIFORNIA: HUMBOLDT COUNTY: FERNDALE",
    "LATITUDE":" PETROLIA",
    "LONGITUDE":"40.368",
    "REGION_CODE":"-124.316",
    "DEATHS":150,
    "DEATHS_DESCRIPTION":null,
    "MISSING":null,
    "MISSING_DESCRIPTION":"",
    "INJURIES":null,
    "INJURIES_DESCRIPTION":98,
    "DAMAGE_MILLIONS_DOLLARS":2,
    "DAMAGE_DESCRIPTION":75,
    "HOUSES_DESTROYED":4,
    "HOUSES_DESTROYED_DESCRIPTION":null,
    "HOUSES_DAMAGED":null,
    "HOUSES_DAMAGED_DESCRIPTION":null,
    "TOTAL_DEATHS":null,
    "TOTAL_DEATHS_DESCRIPTION":null,
    "TOTAL_MISSING":null,
    "TOTAL_MISSING_DESCRIPTION":"",
    "TOTAL_INJURIES":null,
    "TOTAL_INJURIES_DESCRIPTION":98,
    "TOTAL_DAMAGE_MILLIONS_DOLLARS":2,
    "TOTAL_DAMAGE_DESCRIPTION":75,
    "TOTAL_HOUSES_DESTROYED":4,
    "TOTAL_HOUSES_DESTROYED_DESCRIPTION":null,
    "TOTAL_HOUSES_DAMAGED":null,
    "TOTAL_HOUSES_DAMAGED_DESCRIPTION":null
  },
  {
    "I_D":5328,
    "FLAG_TSUNAMI":"",
    "YEAR":1992,
    "MONTH":6,
    "DAY":28,
    "HOUR":11,
    "MINUTE":57,
    "SECOND":34.1,
    "FOCAL_DEPTH":1,
    "EQ_PRIMARY":7.6,
    "EQ_MAG_MW":null,
    "EQ_MAG_MS":7.6,
    "EQ_MAG_MB":6.2,
    "EQ_MAG_ML":null,
    "EQ_MAG_MFA":"",
    "EQ_MAG_UNK":null,
    "INTENSITY":9,
    "COUNTRY":"USA",
    "STATE":"CA",
    "LOCATION_NAME":"CALIFORNIA: LANDERS",
    "LATITUDE":" YUCCA  VALLEY",
    "LONGITUDE":"34.201",
    "REGION_CODE":"-116.436",
    "DEATHS":150,
    "DEATHS_DESCRIPTION":3,
    "MISSING":1,
    "MISSING_DESCRIPTION":"",
    "INJURIES":null,
    "INJURIES_DESCRIPTION":400,
    "DAMAGE_MILLIONS_DOLLARS":3,
    "DAMAGE_DESCRIPTION":92,
    "HOUSES_DESTROYED":4,
    "HOUSES_DESTROYED_DESCRIPTION":null,
    "HOUSES_DAMAGED":null,
    "HOUSES_DAMAGED_DESCRIPTION":null,
    "TOTAL_DEATHS":null,
    "TOTAL_DEATHS_DESCRIPTION":3,
    "TOTAL_MISSING":1,
    "TOTAL_MISSING_DESCRIPTION":"",
    "TOTAL_INJURIES":null,
    "TOTAL_INJURIES_DESCRIPTION":400,
    "TOTAL_DAMAGE_MILLIONS_DOLLARS":3,
    "TOTAL_DAMAGE_DESCRIPTION":92,
    "TOTAL_HOUSES_DESTROYED":4,
    "TOTAL_HOUSES_DESTROYED_DESCRIPTION":null,
    "TOTAL_HOUSES_DAMAGED":null,
    "TOTAL_HOUSES_DAMAGED_DESCRIPTION":null
  },
  {
    "I_D":5330,
    "FLAG_TSUNAMI":"",
    "YEAR":1992,
    "MONTH":6,
    "DAY":28,
    "HOUR":15,
    "MINUTE":5,
    "SECOND":30.7,
    "FOCAL_DEPTH":5,
    "EQ_PRIMARY":6.7,
    "EQ_MAG_MW":null,
    "EQ_MAG_MS":6.7,
    "EQ_MAG_MB":6.3,
    "EQ_MAG_ML":null,
    "EQ_MAG_MFA":"",
    "EQ_MAG_UNK":null,
    "INTENSITY":8,
    "COUNTRY":"USA",
    "STATE":"CA",
    "LOCATION_NAME":"CALIFORNIA: BIG BEAR LAKE",
    "LATITUDE":" BIG BEAR CITY",
    "LONGITUDE":"34.203",
    "REGION_CODE":"-116.827",
    "DEATHS":150,
    "DEATHS_DESCRIPTION":null,
    "MISSING":null,
    "MISSING_DESCRIPTION":"",
    "INJURIES":null,
    "INJURIES_DESCRIPTION":null,
    "DAMAGE_MILLIONS_DOLLARS":2,
    "DAMAGE_DESCRIPTION":null,
    "HOUSES_DESTROYED":2,
    "HOUSES_DESTROYED_DESCRIPTION":null,
    "HOUSES_DAMAGED":null,
    "HOUSES_DAMAGED_DESCRIPTION":null,
    "TOTAL_DEATHS":null,
    "TOTAL_DEATHS_DESCRIPTION":null,
    "TOTAL_MISSING":null,
    "TOTAL_MISSING_DESCRIPTION":"",
    "TOTAL_INJURIES":null,
    "TOTAL_INJURIES_DESCRIPTION":null,
    "TOTAL_DAMAGE_MILLIONS_DOLLARS":2,
    "TOTAL_DAMAGE_DESCRIPTION":null,
    "TOTAL_HOUSES_DESTROYED":2,
    "TOTAL_HOUSES_DESTROYED_DESCRIPTION":null,
    "TOTAL_HOUSES_DAMAGED":null,
    "TOTAL_HOUSES_DAMAGED_DESCRIPTION":null
  },
  {
    "I_D":5372,
    "FLAG_TSUNAMI":"Tsu",
    "YEAR":1994,
    "MONTH":1,
    "DAY":17,
    "HOUR":12,
    "MINUTE":30,
    "SECOND":55.3,
    "FOCAL_DEPTH":18,
    "EQ_PRIMARY":6.7,
    "EQ_MAG_MW":6.7,
    "EQ_MAG_MS":6.8,
    "EQ_MAG_MB":6.4,
    "EQ_MAG_ML":null,
    "EQ_MAG_MFA":"",
    "EQ_MAG_UNK":null,
    "INTENSITY":9,
    "COUNTRY":"USA",
    "STATE":"CA",
    "LOCATION_NAME":"CALIFORNIA:  NORTHRIDGE",
    "LATITUDE":"34.213",
    "LONGITUDE":"-118.537",
    "REGION_CODE":"150",
    "DEATHS":60,
    "DEATHS_DESCRIPTION":2,
    "MISSING":null,
    "MISSING_DESCRIPTION":"",
    "INJURIES":7000,
    "INJURIES_DESCRIPTION":4,
    "DAMAGE_MILLIONS_DOLLARS":40000,
    "DAMAGE_DESCRIPTION":4,
    "HOUSES_DESTROYED":40000,
    "HOUSES_DESTROYED_DESCRIPTION":4,
    "HOUSES_DAMAGED":null,
    "HOUSES_DAMAGED_DESCRIPTION":null,
    "TOTAL_DEATHS":60,
    "TOTAL_DEATHS_DESCRIPTION":2,
    "TOTAL_MISSING":null,
    "TOTAL_MISSING_DESCRIPTION":"",
    "TOTAL_INJURIES":7000,
    "TOTAL_INJURIES_DESCRIPTION":4,
    "TOTAL_DAMAGE_MILLIONS_DOLLARS":40000,
    "TOTAL_DAMAGE_DESCRIPTION":4,
    "TOTAL_HOUSES_DESTROYED":40000,
    "TOTAL_HOUSES_DESTROYED_DESCRIPTION":4,
    "TOTAL_HOUSES_DAMAGED":null,
    "TOTAL_HOUSES_DAMAGED_DESCRIPTION":null
  },
  {
    "I_D":6488,
    "FLAG_TSUNAMI":"Tsu",
    "YEAR":1994,
    "MONTH":9,
    "DAY":1,
    "HOUR":15,
    "MINUTE":15,
    "SECOND":53,
    "FOCAL_DEPTH":10,
    "EQ_PRIMARY":7,
    "EQ_MAG_MW":7,
    "EQ_MAG_MS":7,
    "EQ_MAG_MB":6.6,
    "EQ_MAG_ML":null,
    "EQ_MAG_MFA":"",
    "EQ_MAG_UNK":null,
    "INTENSITY":6,
    "COUNTRY":"USA",
    "STATE":"CA",
    "LOCATION_NAME":"CALIFORNIA:  NORTH:  HONEYDEW",
    "LATITUDE":"40.402",
    "LONGITUDE":"-125.68",
    "REGION_CODE":"150",
    "DEATHS":null,
    "DEATHS_DESCRIPTION":null,
    "MISSING":null,
    "MISSING_DESCRIPTION":"",
    "INJURIES":null,
    "INJURIES_DESCRIPTION":null,
    "DAMAGE_MILLIONS_DOLLARS":null,
    "DAMAGE_DESCRIPTION":1,
    "HOUSES_DESTROYED":null,
    "HOUSES_DESTROYED_DESCRIPTION":null,
    "HOUSES_DAMAGED":null,
    "HOUSES_DAMAGED_DESCRIPTION":null,
    "TOTAL_DEATHS":null,
    "TOTAL_DEATHS_DESCRIPTION":null,
    "TOTAL_MISSING":null,
    "TOTAL_MISSING_DESCRIPTION":"",
    "TOTAL_INJURIES":null,
    "TOTAL_INJURIES_DESCRIPTION":null,
    "TOTAL_DAMAGE_MILLIONS_DOLLARS":null,
    "TOTAL_DAMAGE_DESCRIPTION":1,
    "TOTAL_HOUSES_DESTROYED":null,
    "TOTAL_HOUSES_DESTROYED_DESCRIPTION":null,
    "TOTAL_HOUSES_DAMAGED":null,
    "TOTAL_HOUSES_DAMAGED_DESCRIPTION":null
  },
  {
    "I_D":5395,
    "FLAG_TSUNAMI":"",
    "YEAR":1994,
    "MONTH":12,
    "DAY":26,
    "HOUR":14,
    "MINUTE":10,
    "SECOND":29.1,
    "FOCAL_DEPTH":23,
    "EQ_PRIMARY":5.5,
    "EQ_MAG_MW":5.5,
    "EQ_MAG_MS":5,
    "EQ_MAG_MB":5.1,
    "EQ_MAG_ML":null,
    "EQ_MAG_MFA":"",
    "EQ_MAG_UNK":null,
    "INTENSITY":7,
    "COUNTRY":"USA",
    "STATE":"CA",
    "LOCATION_NAME":"CALIFORNIA:  EUREKA",
    "LATITUDE":" SAMOA",
    "LONGITUDE":" ARCATA",
    "REGION_CODE":" BLUE LAKE",
    "DEATHS":40.741,
    "DEATHS_DESCRIPTION":-124.31,
    "MISSING":150,
    "MISSING_DESCRIPTION":"",
    "INJURIES":null,
    "INJURIES_DESCRIPTION":null,
    "DAMAGE_MILLIONS_DOLLARS":null,
    "DAMAGE_DESCRIPTION":null,
    "HOUSES_DESTROYED":null,
    "HOUSES_DESTROYED_DESCRIPTION":2.1,
    "HOUSES_DAMAGED":2,
    "HOUSES_DAMAGED_DESCRIPTION":null,
    "TOTAL_DEATHS":null,
    "TOTAL_DEATHS_DESCRIPTION":null,
    "TOTAL_MISSING":null,
    "TOTAL_MISSING_DESCRIPTION":"",
    "TOTAL_INJURIES":null,
    "TOTAL_INJURIES_DESCRIPTION":null,
    "TOTAL_DAMAGE_MILLIONS_DOLLARS":null,
    "TOTAL_DAMAGE_DESCRIPTION":null,
    "TOTAL_HOUSES_DESTROYED":null,
    "TOTAL_HOUSES_DESTROYED_DESCRIPTION":2.1,
    "TOTAL_HOUSES_DAMAGED":2,
    "TOTAL_HOUSES_DAMAGED_DESCRIPTION":null
  },
  {
    "I_D":5538,
    "FLAG_TSUNAMI":"",
    "YEAR":1999,
    "MONTH":10,
    "DAY":16,
    "HOUR":9,
    "MINUTE":46,
    "SECOND":44.1,
    "FOCAL_DEPTH":null,
    "EQ_PRIMARY":7.2,
    "EQ_MAG_MW":7.2,
    "EQ_MAG_MS":7.4,
    "EQ_MAG_MB":6.3,
    "EQ_MAG_ML":null,
    "EQ_MAG_MFA":"",
    "EQ_MAG_UNK":null,
    "INTENSITY":7,
    "COUNTRY":"USA",
    "STATE":"CA",
    "LOCATION_NAME":"CALIFORNIA:  LUDLOW",
    "LATITUDE":" LANDERS",
    "LONGITUDE":" TWENTYNINE PALMS",
    "REGION_CODE":"34.594",
    "DEATHS":-116.271,
    "DEATHS_DESCRIPTION":150,
    "MISSING":null,
    "MISSING_DESCRIPTION":"",
    "INJURIES":null,
    "INJURIES_DESCRIPTION":null,
    "DAMAGE_MILLIONS_DOLLARS":4,
    "DAMAGE_DESCRIPTION":1,
    "HOUSES_DESTROYED":null,
    "HOUSES_DESTROYED_DESCRIPTION":1,
    "HOUSES_DAMAGED":null,
    "HOUSES_DAMAGED_DESCRIPTION":null,
    "TOTAL_DEATHS":null,
    "TOTAL_DEATHS_DESCRIPTION":null,
    "TOTAL_MISSING":null,
    "TOTAL_MISSING_DESCRIPTION":"",
    "TOTAL_INJURIES":null,
    "TOTAL_INJURIES_DESCRIPTION":null,
    "TOTAL_DAMAGE_MILLIONS_DOLLARS":4,
    "TOTAL_DAMAGE_DESCRIPTION":1,
    "TOTAL_HOUSES_DESTROYED":null,
    "TOTAL_HOUSES_DESTROYED_DESCRIPTION":1,
    "TOTAL_HOUSES_DAMAGED":null,
    "TOTAL_HOUSES_DAMAGED_DESCRIPTION":null
  },
  {
    "I_D":5576,
    "FLAG_TSUNAMI":"",
    "YEAR":2000,
    "MONTH":9,
    "DAY":3,
    "HOUR":8,
    "MINUTE":36,
    "SECOND":30,
    "FOCAL_DEPTH":10,
    "EQ_PRIMARY":5,
    "EQ_MAG_MW":5,
    "EQ_MAG_MS":4.9,
    "EQ_MAG_MB":4.9,
    "EQ_MAG_ML":null,
    "EQ_MAG_MFA":"",
    "EQ_MAG_UNK":null,
    "INTENSITY":7,
    "COUNTRY":"USA",
    "STATE":"CA",
    "LOCATION_NAME":"CALIFORNIA:  NAPA",
    "LATITUDE":"38.379",
    "LONGITUDE":"-122.413",
    "REGION_CODE":"150",
    "DEATHS":null,
    "DEATHS_DESCRIPTION":null,
    "MISSING":null,
    "MISSING_DESCRIPTION":"",
    "INJURIES":41,
    "INJURIES_DESCRIPTION":1,
    "DAMAGE_MILLIONS_DOLLARS":50,
    "DAMAGE_DESCRIPTION":4,
    "HOUSES_DESTROYED":null,
    "HOUSES_DESTROYED_DESCRIPTION":null,
    "HOUSES_DAMAGED":null,
    "HOUSES_DAMAGED_DESCRIPTION":null,
    "TOTAL_DEATHS":null,
    "TOTAL_DEATHS_DESCRIPTION":null,
    "TOTAL_MISSING":null,
    "TOTAL_MISSING_DESCRIPTION":"",
    "TOTAL_INJURIES":41,
    "TOTAL_INJURIES_DESCRIPTION":1,
    "TOTAL_DAMAGE_MILLIONS_DOLLARS":50,
    "TOTAL_DAMAGE_DESCRIPTION":4,
    "TOTAL_HOUSES_DESTROYED":null,
    "TOTAL_HOUSES_DESTROYED_DESCRIPTION":null,
    "TOTAL_HOUSES_DAMAGED":null,
    "TOTAL_HOUSES_DAMAGED_DESCRIPTION":null
  },
  {
    "I_D":5608,
    "FLAG_TSUNAMI":"",
    "YEAR":2001,
    "MONTH":9,
    "DAY":9,
    "HOUR":23,
    "MINUTE":59,
    "SECOND":18,
    "FOCAL_DEPTH":5,
    "EQ_PRIMARY":4.2,
    "EQ_MAG_MW":null,
    "EQ_MAG_MS":null,
    "EQ_MAG_MB":4.2,
    "EQ_MAG_ML":null,
    "EQ_MAG_MFA":"",
    "EQ_MAG_UNK":null,
    "INTENSITY":6,
    "COUNTRY":"USA",
    "STATE":"CA",
    "LOCATION_NAME":"CALIFORNIA:  LOS ANGELES",
    "LATITUDE":"34.059",
    "LONGITUDE":"-118.387",
    "REGION_CODE":"150",
    "DEATHS":null,
    "DEATHS_DESCRIPTION":null,
    "MISSING":null,
    "MISSING_DESCRIPTION":"",
    "INJURIES":null,
    "INJURIES_DESCRIPTION":null,
    "DAMAGE_MILLIONS_DOLLARS":null,
    "DAMAGE_DESCRIPTION":1,
    "HOUSES_DESTROYED":null,
    "HOUSES_DESTROYED_DESCRIPTION":null,
    "HOUSES_DAMAGED":null,
    "HOUSES_DAMAGED_DESCRIPTION":null,
    "TOTAL_DEATHS":null,
    "TOTAL_DEATHS_DESCRIPTION":null,
    "TOTAL_MISSING":null,
    "TOTAL_MISSING_DESCRIPTION":"",
    "TOTAL_INJURIES":null,
    "TOTAL_INJURIES_DESCRIPTION":null,
    "TOTAL_DAMAGE_MILLIONS_DOLLARS":null,
    "TOTAL_DAMAGE_DESCRIPTION":1,
    "TOTAL_HOUSES_DESTROYED":null,
    "TOTAL_HOUSES_DESTROYED_DESCRIPTION":null,
    "TOTAL_HOUSES_DAMAGED":null,
    "TOTAL_HOUSES_DAMAGED_DESCRIPTION":null
  },
  {
    "I_D":5680,
    "FLAG_TSUNAMI":"",
    "YEAR":2003,
    "MONTH":2,
    "DAY":22,
    "HOUR":12,
    "MINUTE":19,
    "SECOND":10.5,
    "FOCAL_DEPTH":1,
    "EQ_PRIMARY":5.2,
    "EQ_MAG_MW":5.2,
    "EQ_MAG_MS":4.8,
    "EQ_MAG_MB":4.9,
    "EQ_MAG_ML":null,
    "EQ_MAG_MFA":"",
    "EQ_MAG_UNK":null,
    "INTENSITY":6,
    "COUNTRY":"USA",
    "STATE":"CA",
    "LOCATION_NAME":"CALIFORNIA:  BIG BEAR CITY",
    "LATITUDE":"34.31",
    "LONGITUDE":"-116.848",
    "REGION_CODE":"150",
    "DEATHS":null,
    "DEATHS_DESCRIPTION":null,
    "MISSING":null,
    "MISSING_DESCRIPTION":"",
    "INJURIES":null,
    "INJURIES_DESCRIPTION":null,
    "DAMAGE_MILLIONS_DOLLARS":null,
    "DAMAGE_DESCRIPTION":1,
    "HOUSES_DESTROYED":null,
    "HOUSES_DESTROYED_DESCRIPTION":null,
    "HOUSES_DAMAGED":null,
    "HOUSES_DAMAGED_DESCRIPTION":null,
    "TOTAL_DEATHS":null,
    "TOTAL_DEATHS_DESCRIPTION":null,
    "TOTAL_MISSING":null,
    "TOTAL_MISSING_DESCRIPTION":"",
    "TOTAL_INJURIES":null,
    "TOTAL_INJURIES_DESCRIPTION":null,
    "TOTAL_DAMAGE_MILLIONS_DOLLARS":null,
    "TOTAL_DAMAGE_DESCRIPTION":1,
    "TOTAL_HOUSES_DESTROYED":null,
    "TOTAL_HOUSES_DESTROYED_DESCRIPTION":null,
    "TOTAL_HOUSES_DAMAGED":null,
    "TOTAL_HOUSES_DAMAGED_DESCRIPTION":null
  },
  {
    "I_D":5749,
    "FLAG_TSUNAMI":"",
    "YEAR":2003,
    "MONTH":12,
    "DAY":22,
    "HOUR":19,
    "MINUTE":15,
    "SECOND":56,
    "FOCAL_DEPTH":8,
    "EQ_PRIMARY":6.6,
    "EQ_MAG_MW":6.6,
    "EQ_MAG_MS":6.4,
    "EQ_MAG_MB":6.1,
    "EQ_MAG_ML":null,
    "EQ_MAG_MFA":"",
    "EQ_MAG_UNK":null,
    "INTENSITY":8,
    "COUNTRY":"USA",
    "STATE":"CA",
    "LOCATION_NAME":"CALIFORNIA:  PASO ROBLES",
    "LATITUDE":"TEMPLETON",
    "LONGITUDE":"ATASCADERO",
    "REGION_CODE":"35.706",
    "DEATHS":-121.102,
    "DEATHS_DESCRIPTION":150,
    "MISSING":2,
    "MISSING_DESCRIPTION":"1",
    "INJURIES":null,
    "INJURIES_DESCRIPTION":null,
    "DAMAGE_MILLIONS_DOLLARS":40,
    "DAMAGE_DESCRIPTION":1,
    "HOUSES_DESTROYED":300,
    "HOUSES_DESTROYED_DESCRIPTION":4,
    "HOUSES_DAMAGED":40,
    "HOUSES_DAMAGED_DESCRIPTION":1,
    "TOTAL_DEATHS":null,
    "TOTAL_DEATHS_DESCRIPTION":null,
    "TOTAL_MISSING":2,
    "TOTAL_MISSING_DESCRIPTION":"1",
    "TOTAL_INJURIES":null,
    "TOTAL_INJURIES_DESCRIPTION":null,
    "TOTAL_DAMAGE_MILLIONS_DOLLARS":40,
    "TOTAL_DAMAGE_DESCRIPTION":1,
    "TOTAL_HOUSES_DESTROYED":300,
    "TOTAL_HOUSES_DESTROYED_DESCRIPTION":4,
    "TOTAL_HOUSES_DAMAGED":null,
    "TOTAL_HOUSES_DAMAGED_DESCRIPTION":null
  },
  {
    "I_D":5803,
    "FLAG_TSUNAMI":"",
    "YEAR":2004,
    "MONTH":9,
    "DAY":28,
    "HOUR":17,
    "MINUTE":15,
    "SECOND":24.2,
    "FOCAL_DEPTH":9,
    "EQ_PRIMARY":6,
    "EQ_MAG_MW":6,
    "EQ_MAG_MS":5.8,
    "EQ_MAG_MB":5.4,
    "EQ_MAG_ML":null,
    "EQ_MAG_MFA":"",
    "EQ_MAG_UNK":null,
    "INTENSITY":6,
    "COUNTRY":"USA",
    "STATE":"CA",
    "LOCATION_NAME":"CALIFORNIA:  CENTRAL: PARKFIELD",
    "LATITUDE":" SAN MIGUEL",
    "LONGITUDE":"35.819",
    "REGION_CODE":"-120.364",
    "DEATHS":150,
    "DEATHS_DESCRIPTION":null,
    "MISSING":null,
    "MISSING_DESCRIPTION":"",
    "INJURIES":null,
    "INJURIES_DESCRIPTION":null,
    "DAMAGE_MILLIONS_DOLLARS":null,
    "DAMAGE_DESCRIPTION":null,
    "HOUSES_DESTROYED":1,
    "HOUSES_DESTROYED_DESCRIPTION":null,
    "HOUSES_DAMAGED":null,
    "HOUSES_DAMAGED_DESCRIPTION":null,
    "TOTAL_DEATHS":null,
    "TOTAL_DEATHS_DESCRIPTION":null,
    "TOTAL_MISSING":null,
    "TOTAL_MISSING_DESCRIPTION":"",
    "TOTAL_INJURIES":null,
    "TOTAL_INJURIES_DESCRIPTION":null,
    "TOTAL_DAMAGE_MILLIONS_DOLLARS":null,
    "TOTAL_DAMAGE_DESCRIPTION":null,
    "TOTAL_HOUSES_DESTROYED":1,
    "TOTAL_HOUSES_DESTROYED_DESCRIPTION":null,
    "TOTAL_HOUSES_DAMAGED":null,
    "TOTAL_HOUSES_DAMAGED_DESCRIPTION":null
  },
  {
    "I_D":6738,
    "FLAG_TSUNAMI":"Tsu",
    "YEAR":2005,
    "MONTH":6,
    "DAY":15,
    "HOUR":2,
    "MINUTE":50,
    "SECOND":53.1,
    "FOCAL_DEPTH":10,
    "EQ_PRIMARY":7.2,
    "EQ_MAG_MW":7.2,
    "EQ_MAG_MS":7.1,
    "EQ_MAG_MB":6.2,
    "EQ_MAG_ML":null,
    "EQ_MAG_MFA":"",
    "EQ_MAG_UNK":null,
    "INTENSITY":4,
    "COUNTRY":"USA",
    "STATE":"CA",
    "LOCATION_NAME":"CALIFORNIA:  OFF COAST NORTHERN",
    "LATITUDE":"41.301",
    "LONGITUDE":"-125.97",
    "REGION_CODE":"150",
    "DEATHS":null,
    "DEATHS_DESCRIPTION":null,
    "MISSING":null,
    "MISSING_DESCRIPTION":"",
    "INJURIES":null,
    "INJURIES_DESCRIPTION":null,
    "DAMAGE_MILLIONS_DOLLARS":null,
    "DAMAGE_DESCRIPTION":null,
    "HOUSES_DESTROYED":null,
    "HOUSES_DESTROYED_DESCRIPTION":null,
    "HOUSES_DAMAGED":null,
    "HOUSES_DAMAGED_DESCRIPTION":null,
    "TOTAL_DEATHS":null,
    "TOTAL_DEATHS_DESCRIPTION":null,
    "TOTAL_MISSING":null,
    "TOTAL_MISSING_DESCRIPTION":"",
    "TOTAL_INJURIES":null,
    "TOTAL_INJURIES_DESCRIPTION":null,
    "TOTAL_DAMAGE_MILLIONS_DOLLARS":null,
    "TOTAL_DAMAGE_DESCRIPTION":null,
    "TOTAL_HOUSES_DESTROYED":null,
    "TOTAL_HOUSES_DESTROYED_DESCRIPTION":null,
    "TOTAL_HOUSES_DAMAGED":null,
    "TOTAL_HOUSES_DAMAGED_DESCRIPTION":null
  },
  {
    "I_D":7596,
    "FLAG_TSUNAMI":"",
    "YEAR":2007,
    "MONTH":7,
    "DAY":20,
    "HOUR":11,
    "MINUTE":42,
    "SECOND":22.3,
    "FOCAL_DEPTH":5,
    "EQ_PRIMARY":4.2,
    "EQ_MAG_MW":4.2,
    "EQ_MAG_MS":null,
    "EQ_MAG_MB":null,
    "EQ_MAG_ML":null,
    "EQ_MAG_MFA":"",
    "EQ_MAG_UNK":null,
    "INTENSITY":null,
    "COUNTRY":"USA",
    "STATE":"CA",
    "LOCATION_NAME":"CALIFORNIA:  MONTCLAIR",
    "LATITUDE":"37.804",
    "LONGITUDE":"-122.193",
    "REGION_CODE":"150",
    "DEATHS":null,
    "DEATHS_DESCRIPTION":null,
    "MISSING":null,
    "MISSING_DESCRIPTION":"",
    "INJURIES":null,
    "INJURIES_DESCRIPTION":null,
    "DAMAGE_MILLIONS_DOLLARS":null,
    "DAMAGE_DESCRIPTION":1,
    "HOUSES_DESTROYED":null,
    "HOUSES_DESTROYED_DESCRIPTION":null,
    "HOUSES_DAMAGED":null,
    "HOUSES_DAMAGED_DESCRIPTION":null,
    "TOTAL_DEATHS":null,
    "TOTAL_DEATHS_DESCRIPTION":null,
    "TOTAL_MISSING":null,
    "TOTAL_MISSING_DESCRIPTION":"",
    "TOTAL_INJURIES":null,
    "TOTAL_INJURIES_DESCRIPTION":null,
    "TOTAL_DAMAGE_MILLIONS_DOLLARS":null,
    "TOTAL_DAMAGE_DESCRIPTION":1,
    "TOTAL_HOUSES_DESTROYED":null,
    "TOTAL_HOUSES_DESTROYED_DESCRIPTION":null,
    "TOTAL_HOUSES_DAMAGED":null,
    "TOTAL_HOUSES_DAMAGED_DESCRIPTION":null
  },
  {
    "I_D":7698,
    "FLAG_TSUNAMI":"",
    "YEAR":2007,
    "MONTH":10,
    "DAY":31,
    "HOUR":3,
    "MINUTE":4,
    "SECOND":54.8,
    "FOCAL_DEPTH":10,
    "EQ_PRIMARY":5.6,
    "EQ_MAG_MW":5.6,
    "EQ_MAG_MS":5.1,
    "EQ_MAG_MB":5.3,
    "EQ_MAG_ML":null,
    "EQ_MAG_MFA":"",
    "EQ_MAG_UNK":null,
    "INTENSITY":null,
    "COUNTRY":"USA",
    "STATE":"CA",
    "LOCATION_NAME":"CALIFORNIA:  SAN JOSE",
    "LATITUDE":"37.434",
    "LONGITUDE":"-121.774",
    "REGION_CODE":"150",
    "DEATHS":null,
    "DEATHS_DESCRIPTION":null,
    "MISSING":null,
    "MISSING_DESCRIPTION":"",
    "INJURIES":null,
    "INJURIES_DESCRIPTION":null,
    "DAMAGE_MILLIONS_DOLLARS":null,
    "DAMAGE_DESCRIPTION":1,
    "HOUSES_DESTROYED":null,
    "HOUSES_DESTROYED_DESCRIPTION":null,
    "HOUSES_DAMAGED":null,
    "HOUSES_DAMAGED_DESCRIPTION":null,
    "TOTAL_DEATHS":null,
    "TOTAL_DEATHS_DESCRIPTION":null,
    "TOTAL_MISSING":null,
    "TOTAL_MISSING_DESCRIPTION":"",
    "TOTAL_INJURIES":null,
    "TOTAL_INJURIES_DESCRIPTION":null,
    "TOTAL_DAMAGE_MILLIONS_DOLLARS":null,
    "TOTAL_DAMAGE_DESCRIPTION":1,
    "TOTAL_HOUSES_DESTROYED":null,
    "TOTAL_HOUSES_DESTROYED_DESCRIPTION":null,
    "TOTAL_HOUSES_DAMAGED":null,
    "TOTAL_HOUSES_DAMAGED_DESCRIPTION":null
  },
  {
    "I_D":8166,
    "FLAG_TSUNAMI":"",
    "YEAR":2008,
    "MONTH":7,
    "DAY":29,
    "HOUR":18,
    "MINUTE":42,
    "SECOND":15.7,
    "FOCAL_DEPTH":15,
    "EQ_PRIMARY":5.4,
    "EQ_MAG_MW":5.4,
    "EQ_MAG_MS":5.5,
    "EQ_MAG_MB":5.5,
    "EQ_MAG_ML":null,
    "EQ_MAG_MFA":"",
    "EQ_MAG_UNK":null,
    "INTENSITY":6,
    "COUNTRY":"USA",
    "STATE":"CA",
    "LOCATION_NAME":"CALIFORNIA:  LOS ANGELES",
    "LATITUDE":"33.953",
    "LONGITUDE":"-117.761",
    "REGION_CODE":"150",
    "DEATHS":null,
    "DEATHS_DESCRIPTION":null,
    "MISSING":null,
    "MISSING_DESCRIPTION":"",
    "INJURIES":8,
    "INJURIES_DESCRIPTION":1,
    "DAMAGE_MILLIONS_DOLLARS":null,
    "DAMAGE_DESCRIPTION":1,
    "HOUSES_DESTROYED":null,
    "HOUSES_DESTROYED_DESCRIPTION":null,
    "HOUSES_DAMAGED":null,
    "HOUSES_DAMAGED_DESCRIPTION":1,
    "TOTAL_DEATHS":null,
    "TOTAL_DEATHS_DESCRIPTION":null,
    "TOTAL_MISSING":null,
    "TOTAL_MISSING_DESCRIPTION":"",
    "TOTAL_INJURIES":8,
    "TOTAL_INJURIES_DESCRIPTION":1,
    "TOTAL_DAMAGE_MILLIONS_DOLLARS":null,
    "TOTAL_DAMAGE_DESCRIPTION":1,
    "TOTAL_HOUSES_DESTROYED":null,
    "TOTAL_HOUSES_DESTROYED_DESCRIPTION":null,
    "TOTAL_HOUSES_DAMAGED":null,
    "TOTAL_HOUSES_DAMAGED_DESCRIPTION":1
  },
  {
    "I_D":8712,
    "FLAG_TSUNAMI":"",
    "YEAR":2010,
    "MONTH":1,
    "DAY":10,
    "HOUR":0,
    "MINUTE":27,
    "SECOND":39.3,
    "FOCAL_DEPTH":29,
    "EQ_PRIMARY":6.5,
    "EQ_MAG_MW":6.5,
    "EQ_MAG_MS":6.3,
    "EQ_MAG_MB":6.5,
    "EQ_MAG_ML":null,
    "EQ_MAG_MFA":"",
    "EQ_MAG_UNK":null,
    "INTENSITY":null,
    "COUNTRY":"USA",
    "STATE":"CA",
    "LOCATION_NAME":"CALIFORNIA:  OFF COAST NORTHERN",
    "LATITUDE":"40.652",
    "LONGITUDE":"-124.692",
    "REGION_CODE":"150",
    "DEATHS":null,
    "DEATHS_DESCRIPTION":null,
    "MISSING":null,
    "MISSING_DESCRIPTION":"",
    "INJURIES":30,
    "INJURIES_DESCRIPTION":1,
    "DAMAGE_MILLIONS_DOLLARS":21.8,
    "DAMAGE_DESCRIPTION":3,
    "HOUSES_DESTROYED":null,
    "HOUSES_DESTROYED_DESCRIPTION":null,
    "HOUSES_DAMAGED":null,
    "HOUSES_DAMAGED_DESCRIPTION":null,
    "TOTAL_DEATHS":null,
    "TOTAL_DEATHS_DESCRIPTION":null,
    "TOTAL_MISSING":null,
    "TOTAL_MISSING_DESCRIPTION":"",
    "TOTAL_INJURIES":30,
    "TOTAL_INJURIES_DESCRIPTION":1,
    "TOTAL_DAMAGE_MILLIONS_DOLLARS":21.8,
    "TOTAL_DAMAGE_DESCRIPTION":3,
    "TOTAL_HOUSES_DESTROYED":null,
    "TOTAL_HOUSES_DESTROYED_DESCRIPTION":null,
    "TOTAL_HOUSES_DAMAGED":null,
    "TOTAL_HOUSES_DAMAGED_DESCRIPTION":null
  },
  {
    "I_D":10082,
    "FLAG_TSUNAMI":"",
    "YEAR":2014,
    "MONTH":3,
    "DAY":29,
    "HOUR":4,
    "MINUTE":9,
    "SECOND":42,
    "FOCAL_DEPTH":5,
    "EQ_PRIMARY":5.1,
    "EQ_MAG_MW":5.1,
    "EQ_MAG_MS":null,
    "EQ_MAG_MB":null,
    "EQ_MAG_ML":null,
    "EQ_MAG_MFA":"",
    "EQ_MAG_UNK":null,
    "INTENSITY":6,
    "COUNTRY":"USA",
    "STATE":"CA",
    "LOCATION_NAME":"CALIFORNIA:  LA HABRA",
    "LATITUDE":" BREA",
    "LONGITUDE":" FULLERTON",
    "REGION_CODE":"33.932",
    "DEATHS":-117.917,
    "DEATHS_DESCRIPTION":150,
    "MISSING":null,
    "MISSING_DESCRIPTION":"",
    "INJURIES":null,
    "INJURIES_DESCRIPTION":null,
    "DAMAGE_MILLIONS_DOLLARS":null,
    "DAMAGE_DESCRIPTION":1,
    "HOUSES_DESTROYED":10.8,
    "HOUSES_DESTROYED_DESCRIPTION":3,
    "HOUSES_DAMAGED":null,
    "HOUSES_DAMAGED_DESCRIPTION":null,
    "TOTAL_DEATHS":null,
    "TOTAL_DEATHS_DESCRIPTION":2,
    "TOTAL_MISSING":null,
    "TOTAL_MISSING_DESCRIPTION":"",
    "TOTAL_INJURIES":null,
    "TOTAL_INJURIES_DESCRIPTION":null,
    "TOTAL_DAMAGE_MILLIONS_DOLLARS":null,
    "TOTAL_DAMAGE_DESCRIPTION":1,
    "TOTAL_HOUSES_DESTROYED":10.8,
    "TOTAL_HOUSES_DESTROYED_DESCRIPTION":3,
    "TOTAL_HOUSES_DAMAGED":null,
    "TOTAL_HOUSES_DAMAGED_DESCRIPTION":null
  },
  {
    "I_D":10110,
    "FLAG_TSUNAMI":"",
    "YEAR":2014,
    "MONTH":8,
    "DAY":24,
    "HOUR":10,
    "MINUTE":20,
    "SECOND":44,
    "FOCAL_DEPTH":11,
    "EQ_PRIMARY":6,
    "EQ_MAG_MW":6,
    "EQ_MAG_MS":null,
    "EQ_MAG_MB":null,
    "EQ_MAG_ML":null,
    "EQ_MAG_MFA":"",
    "EQ_MAG_UNK":null,
    "INTENSITY":null,
    "COUNTRY":"USA",
    "STATE":"CA",
    "LOCATION_NAME":"CALIFORNIA:  NAPA",
    "LATITUDE":" VALLEJO",
    "LONGITUDE":"38.22",
    "REGION_CODE":"-122.313",
    "DEATHS":150,
    "DEATHS_DESCRIPTION":1,
    "MISSING":1,
    "MISSING_DESCRIPTION":"",
    "INJURIES":null,
    "INJURIES_DESCRIPTION":172,
    "DAMAGE_MILLIONS_DOLLARS":3,
    "DAMAGE_DESCRIPTION":362,
    "HOUSES_DESTROYED":4,
    "HOUSES_DESTROYED_DESCRIPTION":126,
    "HOUSES_DAMAGED":3,
    "HOUSES_DAMAGED_DESCRIPTION":532,
    "TOTAL_DEATHS":3,
    "TOTAL_DEATHS_DESCRIPTION":1,
    "TOTAL_MISSING":1,
    "TOTAL_MISSING_DESCRIPTION":"",
    "TOTAL_INJURIES":null,
    "TOTAL_INJURIES_DESCRIPTION":172,
    "TOTAL_DAMAGE_MILLIONS_DOLLARS":3,
    "TOTAL_DAMAGE_DESCRIPTION":362,
    "TOTAL_HOUSES_DESTROYED":4,
    "TOTAL_HOUSES_DESTROYED_DESCRIPTION":126,
    "TOTAL_HOUSES_DAMAGED":3,
    "TOTAL_HOUSES_DAMAGED_DESCRIPTION":532
  }
]
